Workbook
Name Ctr_AllManagers: Lists!$B$1:$B$75
Name Ctr_AmitChakraborty: Lists!$C$1:$C$11
Name Ctr_Barna: Lists!$D$1:$D$12
Name Ctr_BhargavChalla: Lists!$E$1:$E$7
Name Ctr_GagandeepSinghSachar: Lists!$F$1:$F$11
Name Ctr_MahaboobBasha: Lists!$G$1:$G$4
Name Ctr_Phani: Lists!$H$1:$H$15
Name Ctr_RaghavenderRao: Lists!$I$1:$I$4
Name Ctr_SJakir: Lists!$J$1:$J$16
Name Ctr_SanjayKumarTarai: Lists!$K$1:$K$3

Sheet Dashboard
A1: Unannounced Monthly Centre Visit — Interactive Dashboard
A3: Second Level Manager field audits · 1 Jul 2026–23 Jul 2026 · Select a Manager and/or Centre below to filter every table and chart on this sheet
A5: Second Level Manager: | B5: All Managers | D5: Centre: | E5: All Centres
A6: The Centre list narrows to the selected Manager's centres — if you switch Manager, reopen the Centre dropdown and pick again.
A7: internal: | B7: =IF($B$5="All Managers","*",$B$5) | C7: =IF($E$5="All Centres","*",$E$5)
A9: Visits in View | C9: Overall % Need Improvement | E9: Weakest Section | G9: Top Gap Item
A10: =COUNTIFS(Visits!$A$2:$A$75,$B$7,Visits!$B$2:$B$75,$C$7) | C10: =IFERROR((SUMIFS(Visits!$F$2:$F$75,Visits!$A$2:$A$75,$B$7,Visits!$B$2:$B$75,$C$7)+SUMIFS(Visits!$I$2:$I$75,Visits!$A$2:$A$75,$B$7,Visits!$B$2:$B$75,$C$7)+SUMIFS(Visits!$L$2:$L$75,Visits!$A$2:$A$75,$B$7,Visits!$B$2:$B$75,$C$7)+SUMIFS(Visits!$O$2:$O$75,Visits!$A$2:$A$75,$B$7,Visits!$B$2:$B$75,$C$7))/((SUMIFS(Visits!$E$2:$E$75,Visits!$A$2:$A$75,$B$7,Visits!$B$2:$B$75,$C$7)+SUMIFS(Visits!$F$2:$F$75,Visits!$A$2:$A$75,$B$7,Visits!$B$2:$B$75,$C$7))+(SUMIFS(Visits!$H$2:$H$75,Visits!$A$2:$A$75,$B$7,Visits!$B$2:$B$75,$C$7)+SUMIFS(Visits!$I$2:$I$75,Visits!$A$2:$A$75,$B$7,Visits!$B$2:$B$75,$C$7))+(SUMIFS(Visits!$K$2:$K$75,Visits!$A$2:$A$75,$B$7,Visits!$B$2:$B$75,$C$7)+SUMIFS(Visits!$L$2:$L$75,Visits!$A$2:$A$75,$B$7,Visits!$B$2:$B$75,$C$7))+(SUMIFS(Visits!$N$2:$N$75,Visits!$A$2:$A$75,$B$7,Visits!$B$2:$B$75,$C$7)+SUMIFS(Visits!$O$2:$O$75,Visits!$A$2:$A$75,$B$7,Visits!$B$2:$B$75,$C$7))),0) | E10: =INDEX($A$18:$A$21,MATCH(MAX($E$18:$E$21),$E$18:$E$21,0)) | G10: =B26
A12: visits matching current filter | C12: ="Of "&SUM($B$18:$D$21)&" checklist items: "&SUM($C$18:$C$21)&" Need Improvement, "&SUM($D$18:$D$21)&" Not Applicable." | E12: ="Of "&(INDEX($B$18:$B$21,MATCH(MAX($E$18:$E$21),$E$18:$E$21,0))+INDEX($C$18:$C$21,MATCH(MAX($E$18:$E$21),$E$18:$E$21,0))+INDEX($D$18:$D$21,MATCH(MAX($E$18:$E$21),$E$18:$E$21,0)))&" items in this section: "&INDEX($C$18:$C$21,MATCH(MAX($E$18:$E$21),$E$18:$E$21,0))&" Need Improvement, "&INDEX($D$18:$D$21,MATCH(MAX($E$18:$E$21),$E$18:$E$21,0))&" Not Applicable ("&TEXT(MAX($E$18:$E$21),"0.0%")&")." | G12: most-flagged single checklist item in view
A16: Section-Wise Compliance
A17: Section | B17: All is Well | C17: Need Improvement | D17: Not Applicable | E17: % Need Improvement
A18: Data Check | B18: =SUMIFS(Visits!$E$2:$E$75,Visits!$A$2:$A$75,$B$7,Visits!$B$2:$B$75,$C$7) | C18: =SUMIFS(Visits!$F$2:$F$75,Visits!$A$2:$A$75,$B$7,Visits!$B$2:$B$75,$C$7) | D18: =SUMIFS(Visits!$G$2:$G$75,Visits!$A$2:$A$75,$B$7,Visits!$B$2:$B$75,$C$7) | E18: =IFERROR(C18/(B18+C18),0)
A19: Infra Check | B19: =SUMIFS(Visits!$H$2:$H$75,Visits!$A$2:$A$75,$B$7,Visits!$B$2:$B$75,$C$7) | C19: =SUMIFS(Visits!$I$2:$I$75,Visits!$A$2:$A$75,$B$7,Visits!$B$2:$B$75,$C$7) | D19: =SUMIFS(Visits!$J$2:$J$75,Visits!$A$2:$A$75,$B$7,Visits!$B$2:$B$75,$C$7) | E19: =IFERROR(C19/(B19+C19),0)
A20: Process Check | B20: =SUMIFS(Visits!$K$2:$K$75,Visits!$A$2:$A$75,$B$7,Visits!$B$2:$B$75,$C$7) | C20: =SUMIFS(Visits!$L$2:$L$75,Visits!$A$2:$A$75,$B$7,Visits!$B$2:$B$75,$C$7) | D20: =SUMIFS(Visits!$M$2:$M$75,Visits!$A$2:$A$75,$B$7,Visits!$B$2:$B$75,$C$7) | E20: =IFERROR(C20/(B20+C20),0)
A21: Aspirant Interaction | B21: =SUMIFS(Visits!$N$2:$N$75,Visits!$A$2:$A$75,$B$7,Visits!$B$2:$B$75,$C$7) | C21: =SUMIFS(Visits!$O$2:$O$75,Visits!$A$2:$A$75,$B$7,Visits!$B$2:$B$75,$C$7) | D21: =SUMIFS(Visits!$P$2:$P$75,Visits!$A$2:$A$75,$B$7,Visits!$B$2:$B$75,$C$7) | E21: =IFERROR(C21/(B21+C21),0)
A23: Need Improvement Spotlight — Top 15 Checklist Items
A24: Ranked by number of “Need Improvement” flags among visits currently in view
A25: Section | B25: Checklist Item | C25: Need Improvement | D25: Applicable N | E25: % Need Improvement
A26: =IFERROR(INDEX(ItemStats!$A$2:$A$50,MATCH(LARGE(ItemStats!$G$2:$G$50,1),ItemStats!$G$2:$G$50,0)),"") | B26: =IFERROR(INDEX(ItemStats!$B$2:$B$50,MATCH(LARGE(ItemStats!$G$2:$G$50,1),ItemStats!$G$2:$G$50,0)),"") | C26: =IFERROR(INDEX(ItemStats!$C$2:$C$50,MATCH(LARGE(ItemStats!$G$2:$G$50,1),ItemStats!$G$2:$G$50,0)),"") | D26: =IFERROR(INDEX(ItemStats!$E$2:$E$50,MATCH(LARGE(ItemStats!$G$2:$G$50,1),ItemStats!$G$2:$G$50,0)),"") | E26: =IFERROR(INDEX(ItemStats!$F$2:$F$50,MATCH(LARGE(ItemStats!$G$2:$G$50,1),ItemStats!$G$2:$G$50,0)),"")
A27: =IFERROR(INDEX(ItemStats!$A$2:$A$50,MATCH(LARGE(ItemStats!$G$2:$G$50,2),ItemStats!$G$2:$G$50,0)),"") | B27: =IFERROR(INDEX(ItemStats!$B$2:$B$50,MATCH(LARGE(ItemStats!$G$2:$G$50,2),ItemStats!$G$2:$G$50,0)),"") | C27: =IFERROR(INDEX(ItemStats!$C$2:$C$50,MATCH(LARGE(ItemStats!$G$2:$G$50,2),ItemStats!$G$2:$G$50,0)),"") | D27: =IFERROR(INDEX(ItemStats!$E$2:$E$50,MATCH(LARGE(ItemStats!$G$2:$G$50,2),ItemStats!$G$2:$G$50,0)),"") | E27: =IFERROR(INDEX(ItemStats!$F$2:$F$50,MATCH(LARGE(ItemStats!$G$2:$G$50,2),ItemStats!$G$2:$G$50,0)),"")
A28: =IFERROR(INDEX(ItemStats!$A$2:$A$50,MATCH(LARGE(ItemStats!$G$2:$G$50,3),ItemStats!$G$2:$G$50,0)),"") | B28: =IFERROR(INDEX(ItemStats!$B$2:$B$50,MATCH(LARGE(ItemStats!$G$2:$G$50,3),ItemStats!$G$2:$G$50,0)),"") | C28: =IFERROR(INDEX(ItemStats!$C$2:$C$50,MATCH(LARGE(ItemStats!$G$2:$G$50,3),ItemStats!$G$2:$G$50,0)),"") | D28: =IFERROR(INDEX(ItemStats!$E$2:$E$50,MATCH(LARGE(ItemStats!$G$2:$G$50,3),ItemStats!$G$2:$G$50,0)),"") | E28: =IFERROR(INDEX(ItemStats!$F$2:$F$50,MATCH(LARGE(ItemStats!$G$2:$G$50,3),ItemStats!$G$2:$G$50,0)),"")
A29: =IFERROR(INDEX(ItemStats!$A$2:$A$50,MATCH(LARGE(ItemStats!$G$2:$G$50,4),ItemStats!$G$2:$G$50,0)),"") | B29: =IFERROR(INDEX(ItemStats!$B$2:$B$50,MATCH(LARGE(ItemStats!$G$2:$G$50,4),ItemStats!$G$2:$G$50,0)),"") | C29: =IFERROR(INDEX(ItemStats!$C$2:$C$50,MATCH(LARGE(ItemStats!$G$2:$G$50,4),ItemStats!$G$2:$G$50,0)),"") | D29: =IFERROR(INDEX(ItemStats!$E$2:$E$50,MATCH(LARGE(ItemStats!$G$2:$G$50,4),ItemStats!$G$2:$G$50,0)),"") | E29: =IFERROR(INDEX(ItemStats!$F$2:$F$50,MATCH(LARGE(ItemStats!$G$2:$G$50,4),ItemStats!$G$2:$G$50,0)),"")
A30: =IFERROR(INDEX(ItemStats!$A$2:$A$50,MATCH(LARGE(ItemStats!$G$2:$G$50,5),ItemStats!$G$2:$G$50,0)),"") | B30: =IFERROR(INDEX(ItemStats!$B$2:$B$50,MATCH(LARGE(ItemStats!$G$2:$G$50,5),ItemStats!$G$2:$G$50,0)),"") | C30: =IFERROR(INDEX(ItemStats!$C$2:$C$50,MATCH(LARGE(ItemStats!$G$2:$G$50,5),ItemStats!$G$2:$G$50,0)),"") | D30: =IFERROR(INDEX(ItemStats!$E$2:$E$50,MATCH(LARGE(ItemStats!$G$2:$G$50,5),ItemStats!$G$2:$G$50,0)),"") | E30: =IFERROR(INDEX(ItemStats!$F$2:$F$50,MATCH(LARGE(ItemStats!$G$2:$G$50,5),ItemStats!$G$2:$G$50,0)),"")
A31: =IFERROR(INDEX(ItemStats!$A$2:$A$50,MATCH(LARGE(ItemStats!$G$2:$G$50,6),ItemStats!$G$2:$G$50,0)),"") | B31: =IFERROR(INDEX(ItemStats!$B$2:$B$50,MATCH(LARGE(ItemStats!$G$2:$G$50,6),ItemStats!$G$2:$G$50,0)),"") | C31: =IFERROR(INDEX(ItemStats!$C$2:$C$50,MATCH(LARGE(ItemStats!$G$2:$G$50,6),ItemStats!$G$2:$G$50,0)),"") | D31: =IFERROR(INDEX(ItemStats!$E$2:$E$50,MATCH(LARGE(ItemStats!$G$2:$G$50,6),ItemStats!$G$2:$G$50,0)),"") | E31: =IFERROR(INDEX(ItemStats!$F$2:$F$50,MATCH(LARGE(ItemStats!$G$2:$G$50,6),ItemStats!$G$2:$G$50,0)),"")
A32: =IFERROR(INDEX(ItemStats!$A$2:$A$50,MATCH(LARGE(ItemStats!$G$2:$G$50,7),ItemStats!$G$2:$G$50,0)),"") | B32: =IFERROR(INDEX(ItemStats!$B$2:$B$50,MATCH(LARGE(ItemStats!$G$2:$G$50,7),ItemStats!$G$2:$G$50,0)),"") | C32: =IFERROR(INDEX(ItemStats!$C$2:$C$50,MATCH(LARGE(ItemStats!$G$2:$G$50,7),ItemStats!$G$2:$G$50,0)),"") | D32: =IFERROR(INDEX(ItemStats!$E$2:$E$50,MATCH(LARGE(ItemStats!$G$2:$G$50,7),ItemStats!$G$2:$G$50,0)),"") | E32: =IFERROR(INDEX(ItemStats!$F$2:$F$50,MATCH(LARGE(ItemStats!$G$2:$G$50,7),ItemStats!$G$2:$G$50,0)),"")
A33: =IFERROR(INDEX(ItemStats!$A$2:$A$50,MATCH(LARGE(ItemStats!$G$2:$G$50,8),ItemStats!$G$2:$G$50,0)),"") | B33: =IFERROR(INDEX(ItemStats!$B$2:$B$50,MATCH(LARGE(ItemStats!$G$2:$G$50,8),ItemStats!$G$2:$G$50,0)),"") | C33: =IFERROR(INDEX(ItemStats!$C$2:$C$50,MATCH(LARGE(ItemStats!$G$2:$G$50,8),ItemStats!$G$2:$G$50,0)),"") | D33: =IFERROR(INDEX(ItemStats!$E$2:$E$50,MATCH(LARGE(ItemStats!$G$2:$G$50,8),ItemStats!$G$2:$G$50,0)),"") | E33: =IFERROR(INDEX(ItemStats!$F$2:$F$50,MATCH(LARGE(ItemStats!$G$2:$G$50,8),ItemStats!$G$2:$G$50,0)),"")
A34: =IFERROR(INDEX(ItemStats!$A$2:$A$50,MATCH(LARGE(ItemStats!$G$2:$G$50,9),ItemStats!$G$2:$G$50,0)),"") | B34: =IFERROR(INDEX(ItemStats!$B$2:$B$50,MATCH(LARGE(ItemStats!$G$2:$G$50,9),ItemStats!$G$2:$G$50,0)),"") | C34: =IFERROR(INDEX(ItemStats!$C$2:$C$50,MATCH(LARGE(ItemStats!$G$2:$G$50,9),ItemStats!$G$2:$G$50,0)),"") | D34: =IFERROR(INDEX(ItemStats!$E$2:$E$50,MATCH(LARGE(ItemStats!$G$2:$G$50,9),ItemStats!$G$2:$G$50,0)),"") | E34: =IFERROR(INDEX(ItemStats!$F$2:$F$50,MATCH(LARGE(ItemStats!$G$2:$G$50,9),ItemStats!$G$2:$G$50,0)),"")
A35: =IFERROR(INDEX(ItemStats!$A$2:$A$50,MATCH(LARGE(ItemStats!$G$2:$G$50,10),ItemStats!$G$2:$G$50,0)),"") | B35: =IFERROR(INDEX(ItemStats!$B$2:$B$50,MATCH(LARGE(ItemStats!$G$2:$G$50,10),ItemStats!$G$2:$G$50,0)),"") | C35: =IFERROR(INDEX(ItemStats!$C$2:$C$50,MATCH(LARGE(ItemStats!$G$2:$G$50,10),ItemStats!$G$2:$G$50,0)),"") | D35: =IFERROR(INDEX(ItemStats!$E$2:$E$50,MATCH(LARGE(ItemStats!$G$2:$G$50,10),ItemStats!$G$2:$G$50,0)),"") | E35: =IFERROR(INDEX(ItemStats!$F$2:$F$50,MATCH(LARGE(ItemStats!$G$2:$G$50,10),ItemStats!$G$2:$G$50,0)),"")
A36: =IFERROR(INDEX(ItemStats!$A$2:$A$50,MATCH(LARGE(ItemStats!$G$2:$G$50,11),ItemStats!$G$2:$G$50,0)),"") | B36: =IFERROR(INDEX(ItemStats!$B$2:$B$50,MATCH(LARGE(ItemStats!$G$2:$G$50,11),ItemStats!$G$2:$G$50,0)),"") | C36: =IFERROR(INDEX(ItemStats!$C$2:$C$50,MATCH(LARGE(ItemStats!$G$2:$G$50,11),ItemStats!$G$2:$G$50,0)),"") | D36: =IFERROR(INDEX(ItemStats!$E$2:$E$50,MATCH(LARGE(ItemStats!$G$2:$G$50,11),ItemStats!$G$2:$G$50,0)),"") | E36: =IFERROR(INDEX(ItemStats!$F$2:$F$50,MATCH(LARGE(ItemStats!$G$2:$G$50,11),ItemStats!$G$2:$G$50,0)),"")
A37: =IFERROR(INDEX(ItemStats!$A$2:$A$50,MATCH(LARGE(ItemStats!$G$2:$G$50,12),ItemStats!$G$2:$G$50,0)),"") | B37: =IFERROR(INDEX(ItemStats!$B$2:$B$50,MATCH(LARGE(ItemStats!$G$2:$G$50,12),ItemStats!$G$2:$G$50,0)),"") | C37: =IFERROR(INDEX(ItemStats!$C$2:$C$50,MATCH(LARGE(ItemStats!$G$2:$G$50,12),ItemStats!$G$2:$G$50,0)),"") | D37: =IFERROR(INDEX(ItemStats!$E$2:$E$50,MATCH(LARGE(ItemStats!$G$2:$G$50,12),ItemStats!$G$2:$G$50,0)),"") | E37: =IFERROR(INDEX(ItemStats!$F$2:$F$50,MATCH(LARGE(ItemStats!$G$2:$G$50,12),ItemStats!$G$2:$G$50,0)),"")
A38: =IFERROR(INDEX(ItemStats!$A$2:$A$50,MATCH(LARGE(ItemStats!$G$2:$G$50,13),ItemStats!$G$2:$G$50,0)),"") | B38: =IFERROR(INDEX(ItemStats!$B$2:$B$50,MATCH(LARGE(ItemStats!$G$2:$G$50,13),ItemStats!$G$2:$G$50,0)),"") | C38: =IFERROR(INDEX(ItemStats!$C$2:$C$50,MATCH(LARGE(ItemStats!$G$2:$G$50,13),ItemStats!$G$2:$G$50,0)),"") | D38: =IFERROR(INDEX(ItemStats!$E$2:$E$50,MATCH(LARGE(ItemStats!$G$2:$G$50,13),ItemStats!$G$2:$G$50,0)),"") | E38: =IFERROR(INDEX(ItemStats!$F$2:$F$50,MATCH(LARGE(ItemStats!$G$2:$G$50,13),ItemStats!$G$2:$G$50,0)),"")
A39: =IFERROR(INDEX(ItemStats!$A$2:$A$50,MATCH(LARGE(ItemStats!$G$2:$G$50,14),ItemStats!$G$2:$G$50,0)),"") | B39: =IFERROR(INDEX(ItemStats!$B$2:$B$50,MATCH(LARGE(ItemStats!$G$2:$G$50,14),ItemStats!$G$2:$G$50,0)),"") | C39: =IFERROR(INDEX(ItemStats!$C$2:$C$50,MATCH(LARGE(ItemStats!$G$2:$G$50,14),ItemStats!$G$2:$G$50,0)),"") | D39: =IFERROR(INDEX(ItemStats!$E$2:$E$50,MATCH(LARGE(ItemStats!$G$2:$G$50,14),ItemStats!$G$2:$G$50,0)),"") | E39: =IFERROR(INDEX(ItemStats!$F$2:$F$50,MATCH(LARGE(ItemStats!$G$2:$G$50,14),ItemStats!$G$2:$G$50,0)),"")
A40: =IFERROR(INDEX(ItemStats!$A$2:$A$50,MATCH(LARGE(ItemStats!$G$2:$G$50,15),ItemStats!$G$2:$G$50,0)),"") | B40: =IFERROR(INDEX(ItemStats!$B$2:$B$50,MATCH(LARGE(ItemStats!$G$2:$G$50,15),ItemStats!$G$2:$G$50,0)),"") | C40: =IFERROR(INDEX(ItemStats!$C$2:$C$50,MATCH(LARGE(ItemStats!$G$2:$G$50,15),ItemStats!$G$2:$G$50,0)),"") | D40: =IFERROR(INDEX(ItemStats!$E$2:$E$50,MATCH(LARGE(ItemStats!$G$2:$G$50,15),ItemStats!$G$2:$G$50,0)),"") | E40: =IFERROR(INDEX(ItemStats!$F$2:$F$50,MATCH(LARGE(ItemStats!$G$2:$G$50,15),ItemStats!$G$2:$G$50,0)),"")

Sheet Reflections
A1: Field Reflections — filtered by Dashboard selection
A3: This list updates automatically based on the Manager / Centre selected on the Dashboard sheet.
A5: Centre | B5: Manager | C5: Program | D5: Date | E5: Key bottleneck resolved | F5: Placement % action | G5: Batch on-time action
A6: =IFERROR(INDEX(Visits!$B$2:$B$75,MATCH(1,Visits!$U$2:$U$75,0)),"") | B6: =IFERROR(INDEX(Visits!$A$2:$A$75,MATCH(1,Visits!$U$2:$U$75,0)),"") | C6: =IFERROR(INDEX(Visits!$C$2:$C$75,MATCH(1,Visits!$U$2:$U$75,0)),"") | D6: =IFERROR(INDEX(Visits!$D$2:$D$75,MATCH(1,Visits!$U$2:$U$75,0)),"") | E6: =IFERROR(INDEX(Visits!$Q$2:$Q$75,MATCH(1,Visits!$U$2:$U$75,0)),"") | F6: =IFERROR(INDEX(Visits!$R$2:$R$75,MATCH(1,Visits!$U$2:$U$75,0)),"") | G6: =IFERROR(INDEX(Visits!$S$2:$S$75,MATCH(1,Visits!$U$2:$U$75,0)),"")
A7: =IFERROR(INDEX(Visits!$B$2:$B$75,MATCH(2,Visits!$U$2:$U$75,0)),"") | B7: =IFERROR(INDEX(Visits!$A$2:$A$75,MATCH(2,Visits!$U$2:$U$75,0)),"") | C7: =IFERROR(INDEX(Visits!$C$2:$C$75,MATCH(2,Visits!$U$2:$U$75,0)),"") | D7: =IFERROR(INDEX(Visits!$D$2:$D$75,MATCH(2,Visits!$U$2:$U$75,0)),"") | E7: =IFERROR(INDEX(Visits!$Q$2:$Q$75,MATCH(2,Visits!$U$2:$U$75,0)),"") | F7: =IFERROR(INDEX(Visits!$R$2:$R$75,MATCH(2,Visits!$U$2:$U$75,0)),"") | G7: =IFERROR(INDEX(Visits!$S$2:$S$75,MATCH(2,Visits!$U$2:$U$75,0)),"")
A8: =IFERROR(INDEX(Visits!$B$2:$B$75,MATCH(3,Visits!$U$2:$U$75,0)),"") | B8: =IFERROR(INDEX(Visits!$A$2:$A$75,MATCH(3,Visits!$U$2:$U$75,0)),"") | C8: =IFERROR(INDEX(Visits!$C$2:$C$75,MATCH(3,Visits!$U$2:$U$75,0)),"") | D8: =IFERROR(INDEX(Visits!$D$2:$D$75,MATCH(3,Visits!$U$2:$U$75,0)),"") | E8: =IFERROR(INDEX(Visits!$Q$2:$Q$75,MATCH(3,Visits!$U$2:$U$75,0)),"") | F8: =IFERROR(INDEX(Visits!$R$2:$R$75,MATCH(3,Visits!$U$2:$U$75,0)),"") | G8: =IFERROR(INDEX(Visits!$S$2:$S$75,MATCH(3,Visits!$U$2:$U$75,0)),"")
A9: =IFERROR(INDEX(Visits!$B$2:$B$75,MATCH(4,Visits!$U$2:$U$75,0)),"") | B9: =IFERROR(INDEX(Visits!$A$2:$A$75,MATCH(4,Visits!$U$2:$U$75,0)),"") | C9: =IFERROR(INDEX(Visits!$C$2:$C$75,MATCH(4,Visits!$U$2:$U$75,0)),"") | D9: =IFERROR(INDEX(Visits!$D$2:$D$75,MATCH(4,Visits!$U$2:$U$75,0)),"") | E9: =IFERROR(INDEX(Visits!$Q$2:$Q$75,MATCH(4,Visits!$U$2:$U$75,0)),"") | F9: =IFERROR(INDEX(Visits!$R$2:$R$75,MATCH(4,Visits!$U$2:$U$75,0)),"") | G9: =IFERROR(INDEX(Visits!$S$2:$S$75,MATCH(4,Visits!$U$2:$U$75,0)),"")
A10: =IFERROR(INDEX(Visits!$B$2:$B$75,MATCH(5,Visits!$U$2:$U$75,0)),"") | B10: =IFERROR(INDEX(Visits!$A$2:$A$75,MATCH(5,Visits!$U$2:$U$75,0)),"") | C10: =IFERROR(INDEX(Visits!$C$2:$C$75,MATCH(5,Visits!$U$2:$U$75,0)),"") | D10: =IFERROR(INDEX(Visits!$D$2:$D$75,MATCH(5,Visits!$U$2:$U$75,0)),"") | E10: =IFERROR(INDEX(Visits!$Q$2:$Q$75,MATCH(5,Visits!$U$2:$U$75,0)),"") | F10: =IFERROR(INDEX(Visits!$R$2:$R$75,MATCH(5,Visits!$U$2:$U$75,0)),"") | G10: =IFERROR(INDEX(Visits!$S$2:$S$75,MATCH(5,Visits!$U$2:$U$75,0)),"")
A11: =IFERROR(INDEX(Visits!$B$2:$B$75,MATCH(6,Visits!$U$2:$U$75,0)),"") | B11: =IFERROR(INDEX(Visits!$A$2:$A$75,MATCH(6,Visits!$U$2:$U$75,0)),"") | C11: =IFERROR(INDEX(Visits!$C$2:$C$75,MATCH(6,Visits!$U$2:$U$75,0)),"") | D11: =IFERROR(INDEX(Visits!$D$2:$D$75,MATCH(6,Visits!$U$2:$U$75,0)),"") | E11: =IFERROR(INDEX(Visits!$Q$2:$Q$75,MATCH(6,Visits!$U$2:$U$75,0)),"") | F11: =IFERROR(INDEX(Visits!$R$2:$R$75,MATCH(6,Visits!$U$2:$U$75,0)),"") | G11: =IFERROR(INDEX(Visits!$S$2:$S$75,MATCH(6,Visits!$U$2:$U$75,0)),"")
A12: =IFERROR(INDEX(Visits!$B$2:$B$75,MATCH(7,Visits!$U$2:$U$75,0)),"") | B12: =IFERROR(INDEX(Visits!$A$2:$A$75,MATCH(7,Visits!$U$2:$U$75,0)),"") | C12: =IFERROR(INDEX(Visits!$C$2:$C$75,MATCH(7,Visits!$U$2:$U$75,0)),"") | D12: =IFERROR(INDEX(Visits!$D$2:$D$75,MATCH(7,Visits!$U$2:$U$75,0)),"") | E12: =IFERROR(INDEX(Visits!$Q$2:$Q$75,MATCH(7,Visits!$U$2:$U$75,0)),"") | F12: =IFERROR(INDEX(Visits!$R$2:$R$75,MATCH(7,Visits!$U$2:$U$75,0)),"") | G12: =IFERROR(INDEX(Visits!$S$2:$S$75,MATCH(7,Visits!$U$2:$U$75,0)),"")
A13: =IFERROR(INDEX(Visits!$B$2:$B$75,MATCH(8,Visits!$U$2:$U$75,0)),"") | B13: =IFERROR(INDEX(Visits!$A$2:$A$75,MATCH(8,Visits!$U$2:$U$75,0)),"") | C13: =IFERROR(INDEX(Visits!$C$2:$C$75,MATCH(8,Visits!$U$2:$U$75,0)),"") | D13: =IFERROR(INDEX(Visits!$D$2:$D$75,MATCH(8,Visits!$U$2:$U$75,0)),"") | E13: =IFERROR(INDEX(Visits!$Q$2:$Q$75,MATCH(8,Visits!$U$2:$U$75,0)),"") | F13: =IFERROR(INDEX(Visits!$R$2:$R$75,MATCH(8,Visits!$U$2:$U$75,0)),"") | G13: =IFERROR(INDEX(Visits!$S$2:$S$75,MATCH(8,Visits!$U$2:$U$75,0)),"")
A14: =IFERROR(INDEX(Visits!$B$2:$B$75,MATCH(9,Visits!$U$2:$U$75,0)),"") | B14: =IFERROR(INDEX(Visits!$A$2:$A$75,MATCH(9,Visits!$U$2:$U$75,0)),"") | C14: =IFERROR(INDEX(Visits!$C$2:$C$75,MATCH(9,Visits!$U$2:$U$75,0)),"") | D14: =IFERROR(INDEX(Visits!$D$2:$D$75,MATCH(9,Visits!$U$2:$U$75,0)),"") | E14: =IFERROR(INDEX(Visits!$Q$2:$Q$75,MATCH(9,Visits!$U$2:$U$75,0)),"") | F14: =IFERROR(INDEX(Visits!$R$2:$R$75,MATCH(9,Visits!$U$2:$U$75,0)),"") | G14: =IFERROR(INDEX(Visits!$S$2:$S$75,MATCH(9,Visits!$U$2:$U$75,0)),"")
A15: =IFERROR(INDEX(Visits!$B$2:$B$75,MATCH(10,Visits!$U$2:$U$75,0)),"") | B15: =IFERROR(INDEX(Visits!$A$2:$A$75,MATCH(10,Visits!$U$2:$U$75,0)),"") | C15: =IFERROR(INDEX(Visits!$C$2:$C$75,MATCH(10,Visits!$U$2:$U$75,0)),"") | D15: =IFERROR(INDEX(Visits!$D$2:$D$75,MATCH(10,Visits!$U$2:$U$75,0)),"") | E15: =IFERROR(INDEX(Visits!$Q$2:$Q$75,MATCH(10,Visits!$U$2:$U$75,0)),"") | F15: =IFERROR(INDEX(Visits!$R$2:$R$75,MATCH(10,Visits!$U$2:$U$75,0)),"") | G15: =IFERROR(INDEX(Visits!$S$2:$S$75,MATCH(10,Visits!$U$2:$U$75,0)),"")
A16: =IFERROR(INDEX(Visits!$B$2:$B$75,MATCH(11,Visits!$U$2:$U$75,0)),"") | B16: =IFERROR(INDEX(Visits!$A$2:$A$75,MATCH(11,Visits!$U$2:$U$75,0)),"") | C16: =IFERROR(INDEX(Visits!$C$2:$C$75,MATCH(11,Visits!$U$2:$U$75,0)),"") | D16: =IFERROR(INDEX(Visits!$D$2:$D$75,MATCH(11,Visits!$U$2:$U$75,0)),"") | E16: =IFERROR(INDEX(Visits!$Q$2:$Q$75,MATCH(11,Visits!$U$2:$U$75,0)),"") | F16: =IFERROR(INDEX(Visits!$R$2:$R$75,MATCH(11,Visits!$U$2:$U$75,0)),"") | G16: =IFERROR(INDEX(Visits!$S$2:$S$75,MATCH(11,Visits!$U$2:$U$75,0)),"")
A17: =IFERROR(INDEX(Visits!$B$2:$B$75,MATCH(12,Visits!$U$2:$U$75,0)),"") | B17: =IFERROR(INDEX(Visits!$A$2:$A$75,MATCH(12,Visits!$U$2:$U$75,0)),"") | C17: =IFERROR(INDEX(Visits!$C$2:$C$75,MATCH(12,Visits!$U$2:$U$75,0)),"") | D17: =IFERROR(INDEX(Visits!$D$2:$D$75,MATCH(12,Visits!$U$2:$U$75,0)),"") | E17: =IFERROR(INDEX(Visits!$Q$2:$Q$75,MATCH(12,Visits!$U$2:$U$75,0)),"") | F17: =IFERROR(INDEX(Visits!$R$2:$R$75,MATCH(12,Visits!$U$2:$U$75,0)),"") | G17: =IFERROR(INDEX(Visits!$S$2:$S$75,MATCH(12,Visits!$U$2:$U$75,0)),"")
A18: =IFERROR(INDEX(Visits!$B$2:$B$75,MATCH(13,Visits!$U$2:$U$75,0)),"") | B18: =IFERROR(INDEX(Visits!$A$2:$A$75,MATCH(13,Visits!$U$2:$U$75,0)),"") | C18: =IFERROR(INDEX(Visits!$C$2:$C$75,MATCH(13,Visits!$U$2:$U$75,0)),"") | D18: =IFERROR(INDEX(Visits!$D$2:$D$75,MATCH(13,Visits!$U$2:$U$75,0)),"") | E18: =IFERROR(INDEX(Visits!$Q$2:$Q$75,MATCH(13,Visits!$U$2:$U$75,0)),"") | F18: =IFERROR(INDEX(Visits!$R$2:$R$75,MATCH(13,Visits!$U$2:$U$75,0)),"") | G18: =IFERROR(INDEX(Visits!$S$2:$S$75,MATCH(13,Visits!$U$2:$U$75,0)),"")
A19: =IFERROR(INDEX(Visits!$B$2:$B$75,MATCH(14,Visits!$U$2:$U$75,0)),"") | B19: =IFERROR(INDEX(Visits!$A$2:$A$75,MATCH(14,Visits!$U$2:$U$75,0)),"") | C19: =IFERROR(INDEX(Visits!$C$2:$C$75,MATCH(14,Visits!$U$2:$U$75,0)),"") | D19: =IFERROR(INDEX(Visits!$D$2:$D$75,MATCH(14,Visits!$U$2:$U$75,0)),"") | E19: =IFERROR(INDEX(Visits!$Q$2:$Q$75,MATCH(14,Visits!$U$2:$U$75,0)),"") | F19: =IFERROR(INDEX(Visits!$R$2:$R$75,MATCH(14,Visits!$U$2:$U$75,0)),"") | G19: =IFERROR(INDEX(Visits!$S$2:$S$75,MATCH(14,Visits!$U$2:$U$75,0)),"")
A20: =IFERROR(INDEX(Visits!$B$2:$B$75,MATCH(15,Visits!$U$2:$U$75,0)),"") | B20: =IFERROR(INDEX(Visits!$A$2:$A$75,MATCH(15,Visits!$U$2:$U$75,0)),"") | C20: =IFERROR(INDEX(Visits!$C$2:$C$75,MATCH(15,Visits!$U$2:$U$75,0)),"") | D20: =IFERROR(INDEX(Visits!$D$2:$D$75,MATCH(15,Visits!$U$2:$U$75,0)),"") | E20: =IFERROR(INDEX(Visits!$Q$2:$Q$75,MATCH(15,Visits!$U$2:$U$75,0)),"") | F20: =IFERROR(INDEX(Visits!$R$2:$R$75,MATCH(15,Visits!$U$2:$U$75,0)),"") | G20: =IFERROR(INDEX(Visits!$S$2:$S$75,MATCH(15,Visits!$U$2:$U$75,0)),"")
A21: =IFERROR(INDEX(Visits!$B$2:$B$75,MATCH(16,Visits!$U$2:$U$75,0)),"") | B21: =IFERROR(INDEX(Visits!$A$2:$A$75,MATCH(16,Visits!$U$2:$U$75,0)),"") | C21: =IFERROR(INDEX(Visits!$C$2:$C$75,MATCH(16,Visits!$U$2:$U$75,0)),"") | D21: =IFERROR(INDEX(Visits!$D$2:$D$75,MATCH(16,Visits!$U$2:$U$75,0)),"") | E21: =IFERROR(INDEX(Visits!$Q$2:$Q$75,MATCH(16,Visits!$U$2:$U$75,0)),"") | F21: =IFERROR(INDEX(Visits!$R$2:$R$75,MATCH(16,Visits!$U$2:$U$75,0)),"") | G21: =IFERROR(INDEX(Visits!$S$2:$S$75,MATCH(16,Visits!$U$2:$U$75,0)),"")
A22: =IFERROR(INDEX(Visits!$B$2:$B$75,MATCH(17,Visits!$U$2:$U$75,0)),"") | B22: =IFERROR(INDEX(Visits!$A$2:$A$75,MATCH(17,Visits!$U$2:$U$75,0)),"") | C22: =IFERROR(INDEX(Visits!$C$2:$C$75,MATCH(17,Visits!$U$2:$U$75,0)),"") | D22: =IFERROR(INDEX(Visits!$D$2:$D$75,MATCH(17,Visits!$U$2:$U$75,0)),"") | E22: =IFERROR(INDEX(Visits!$Q$2:$Q$75,MATCH(17,Visits!$U$2:$U$75,0)),"") | F22: =IFERROR(INDEX(Visits!$R$2:$R$75,MATCH(17,Visits!$U$2:$U$75,0)),"") | G22: =IFERROR(INDEX(Visits!$S$2:$S$75,MATCH(17,Visits!$U$2:$U$75,0)),"")
A23: =IFERROR(INDEX(Visits!$B$2:$B$75,MATCH(18,Visits!$U$2:$U$75,0)),"") | B23: =IFERROR(INDEX(Visits!$A$2:$A$75,MATCH(18,Visits!$U$2:$U$75,0)),"") | C23: =IFERROR(INDEX(Visits!$C$2:$C$75,MATCH(18,Visits!$U$2:$U$75,0)),"") | D23: =IFERROR(INDEX(Visits!$D$2:$D$75,MATCH(18,Visits!$U$2:$U$75,0)),"") | E23: =IFERROR(INDEX(Visits!$Q$2:$Q$75,MATCH(18,Visits!$U$2:$U$75,0)),"") | F23: =IFERROR(INDEX(Visits!$R$2:$R$75,MATCH(18,Visits!$U$2:$U$75,0)),"") | G23: =IFERROR(INDEX(Visits!$S$2:$S$75,MATCH(18,Visits!$U$2:$U$75,0)),"")
A24: =IFERROR(INDEX(Visits!$B$2:$B$75,MATCH(19,Visits!$U$2:$U$75,0)),"") | B24: =IFERROR(INDEX(Visits!$A$2:$A$75,MATCH(19,Visits!$U$2:$U$75,0)),"") | C24: =IFERROR(INDEX(Visits!$C$2:$C$75,MATCH(19,Visits!$U$2:$U$75,0)),"") | D24: =IFERROR(INDEX(Visits!$D$2:$D$75,MATCH(19,Visits!$U$2:$U$75,0)),"") | E24: =IFERROR(INDEX(Visits!$Q$2:$Q$75,MATCH(19,Visits!$U$2:$U$75,0)),"") | F24: =IFERROR(INDEX(Visits!$R$2:$R$75,MATCH(19,Visits!$U$2:$U$75,0)),"") | G24: =IFERROR(INDEX(Visits!$S$2:$S$75,MATCH(19,Visits!$U$2:$U$75,0)),"")
A25: =IFERROR(INDEX(Visits!$B$2:$B$75,MATCH(20,Visits!$U$2:$U$75,0)),"") | B25: =IFERROR(INDEX(Visits!$A$2:$A$75,MATCH(20,Visits!$U$2:$U$75,0)),"") | C25: =IFERROR(INDEX(Visits!$C$2:$C$75,MATCH(20,Visits!$U$2:$U$75,0)),"") | D25: =IFERROR(INDEX(Visits!$D$2:$D$75,MATCH(20,Visits!$U$2:$U$75,0)),"") | E25: =IFERROR(INDEX(Visits!$Q$2:$Q$75,MATCH(20,Visits!$U$2:$U$75,0)),"") | F25: =IFERROR(INDEX(Visits!$R$2:$R$75,MATCH(20,Visits!$U$2:$U$75,0)),"") | G25: =IFERROR(INDEX(Visits!$S$2:$S$75,MATCH(20,Visits!$U$2:$U$75,0)),"")
A26: =IFERROR(INDEX(Visits!$B$2:$B$75,MATCH(21,Visits!$U$2:$U$75,0)),"") | B26: =IFERROR(INDEX(Visits!$A$2:$A$75,MATCH(21,Visits!$U$2:$U$75,0)),"") | C26: =IFERROR(INDEX(Visits!$C$2:$C$75,MATCH(21,Visits!$U$2:$U$75,0)),"") | D26: =IFERROR(INDEX(Visits!$D$2:$D$75,MATCH(21,Visits!$U$2:$U$75,0)),"") | E26: =IFERROR(INDEX(Visits!$Q$2:$Q$75,MATCH(21,Visits!$U$2:$U$75,0)),"") | F26: =IFERROR(INDEX(Visits!$R$2:$R$75,MATCH(21,Visits!$U$2:$U$75,0)),"") | G26: =IFERROR(INDEX(Visits!$S$2:$S$75,MATCH(21,Visits!$U$2:$U$75,0)),"")
A27: =IFERROR(INDEX(Visits!$B$2:$B$75,MATCH(22,Visits!$U$2:$U$75,0)),"") | B27: =IFERROR(INDEX(Visits!$A$2:$A$75,MATCH(22,Visits!$U$2:$U$75,0)),"") | C27: =IFERROR(INDEX(Visits!$C$2:$C$75,MATCH(22,Visits!$U$2:$U$75,0)),"") | D27: =IFERROR(INDEX(Visits!$D$2:$D$75,MATCH(22,Visits!$U$2:$U$75,0)),"") | E27: =IFERROR(INDEX(Visits!$Q$2:$Q$75,MATCH(22,Visits!$U$2:$U$75,0)),"") | F27: =IFERROR(INDEX(Visits!$R$2:$R$75,MATCH(22,Visits!$U$2:$U$75,0)),"") | G27: =IFERROR(INDEX(Visits!$S$2:$S$75,MATCH(22,Visits!$U$2:$U$75,0)),"")
A28: =IFERROR(INDEX(Visits!$B$2:$B$75,MATCH(23,Visits!$U$2:$U$75,0)),"") | B28: =IFERROR(INDEX(Visits!$A$2:$A$75,MATCH(23,Visits!$U$2:$U$75,0)),"") | C28: =IFERROR(INDEX(Visits!$C$2:$C$75,MATCH(23,Visits!$U$2:$U$75,0)),"") | D28: =IFERROR(INDEX(Visits!$D$2:$D$75,MATCH(23,Visits!$U$2:$U$75,0)),"") | E28: =IFERROR(INDEX(Visits!$Q$2:$Q$75,MATCH(23,Visits!$U$2:$U$75,0)),"") | F28: =IFERROR(INDEX(Visits!$R$2:$R$75,MATCH(23,Visits!$U$2:$U$75,0)),"") | G28: =IFERROR(INDEX(Visits!$S$2:$S$75,MATCH(23,Visits!$U$2:$U$75,0)),"")
A29: =IFERROR(INDEX(Visits!$B$2:$B$75,MATCH(24,Visits!$U$2:$U$75,0)),"") | B29: =IFERROR(INDEX(Visits!$A$2:$A$75,MATCH(24,Visits!$U$2:$U$75,0)),"") | C29: =IFERROR(INDEX(Visits!$C$2:$C$75,MATCH(24,Visits!$U$2:$U$75,0)),"") | D29: =IFERROR(INDEX(Visits!$D$2:$D$75,MATCH(24,Visits!$U$2:$U$75,0)),"") | E29: =IFERROR(INDEX(Visits!$Q$2:$Q$75,MATCH(24,Visits!$U$2:$U$75,0)),"") | F29: =IFERROR(INDEX(Visits!$R$2:$R$75,MATCH(24,Visits!$U$2:$U$75,0)),"") | G29: =IFERROR(INDEX(Visits!$S$2:$S$75,MATCH(24,Visits!$U$2:$U$75,0)),"")
A30: =IFERROR(INDEX(Visits!$B$2:$B$75,MATCH(25,Visits!$U$2:$U$75,0)),"") | B30: =IFERROR(INDEX(Visits!$A$2:$A$75,MATCH(25,Visits!$U$2:$U$75,0)),"") | C30: =IFERROR(INDEX(Visits!$C$2:$C$75,MATCH(25,Visits!$U$2:$U$75,0)),"") | D30: =IFERROR(INDEX(Visits!$D$2:$D$75,MATCH(25,Visits!$U$2:$U$75,0)),"") | E30: =IFERROR(INDEX(Visits!$Q$2:$Q$75,MATCH(25,Visits!$U$2:$U$75,0)),"") | F30: =IFERROR(INDEX(Visits!$R$2:$R$75,MATCH(25,Visits!$U$2:$U$75,0)),"") | G30: =IFERROR(INDEX(Visits!$S$2:$S$75,MATCH(25,Visits!$U$2:$U$75,0)),"")
A31: =IFERROR(INDEX(Visits!$B$2:$B$75,MATCH(26,Visits!$U$2:$U$75,0)),"") | B31: =IFERROR(INDEX(Visits!$A$2:$A$75,MATCH(26,Visits!$U$2:$U$75,0)),"") | C31: =IFERROR(INDEX(Visits!$C$2:$C$75,MATCH(26,Visits!$U$2:$U$75,0)),"") | D31: =IFERROR(INDEX(Visits!$D$2:$D$75,MATCH(26,Visits!$U$2:$U$75,0)),"") | E31: =IFERROR(INDEX(Visits!$Q$2:$Q$75,MATCH(26,Visits!$U$2:$U$75,0)),"") | F31: =IFERROR(INDEX(Visits!$R$2:$R$75,MATCH(26,Visits!$U$2:$U$75,0)),"") | G31: =IFERROR(INDEX(Visits!$S$2:$S$75,MATCH(26,Visits!$U$2:$U$75,0)),"")
A32: =IFERROR(INDEX(Visits!$B$2:$B$75,MATCH(27,Visits!$U$2:$U$75,0)),"") | B32: =IFERROR(INDEX(Visits!$A$2:$A$75,MATCH(27,Visits!$U$2:$U$75,0)),"") | C32: =IFERROR(INDEX(Visits!$C$2:$C$75,MATCH(27,Visits!$U$2:$U$75,0)),"") | D32: =IFERROR(INDEX(Visits!$D$2:$D$75,MATCH(27,Visits!$U$2:$U$75,0)),"") | E32: =IFERROR(INDEX(Visits!$Q$2:$Q$75,MATCH(27,Visits!$U$2:$U$75,0)),"") | F32: =IFERROR(INDEX(Visits!$R$2:$R$75,MATCH(27,Visits!$U$2:$U$75,0)),"") | G32: =IFERROR(INDEX(Visits!$S$2:$S$75,MATCH(27,Visits!$U$2:$U$75,0)),"")
A33: =IFERROR(INDEX(Visits!$B$2:$B$75,MATCH(28,Visits!$U$2:$U$75,0)),"") | B33: =IFERROR(INDEX(Visits!$A$2:$A$75,MATCH(28,Visits!$U$2:$U$75,0)),"") | C33: =IFERROR(INDEX(Visits!$C$2:$C$75,MATCH(28,Visits!$U$2:$U$75,0)),"") | D33: =IFERROR(INDEX(Visits!$D$2:$D$75,MATCH(28,Visits!$U$2:$U$75,0)),"") | E33: =IFERROR(INDEX(Visits!$Q$2:$Q$75,MATCH(28,Visits!$U$2:$U$75,0)),"") | F33: =IFERROR(INDEX(Visits!$R$2:$R$75,MATCH(28,Visits!$U$2:$U$75,0)),"") | G33: =IFERROR(INDEX(Visits!$S$2:$S$75,MATCH(28,Visits!$U$2:$U$75,0)),"")
A34: =IFERROR(INDEX(Visits!$B$2:$B$75,MATCH(29,Visits!$U$2:$U$75,0)),"") | B34: =IFERROR(INDEX(Visits!$A$2:$A$75,MATCH(29,Visits!$U$2:$U$75,0)),"") | C34: =IFERROR(INDEX(Visits!$C$2:$C$75,MATCH(29,Visits!$U$2:$U$75,0)),"") | D34: =IFERROR(INDEX(Visits!$D$2:$D$75,MATCH(29,Visits!$U$2:$U$75,0)),"") | E34: =IFERROR(INDEX(Visits!$Q$2:$Q$75,MATCH(29,Visits!$U$2:$U$75,0)),"") | F34: =IFERROR(INDEX(Visits!$R$2:$R$75,MATCH(29,Visits!$U$2:$U$75,0)),"") | G34: =IFERROR(INDEX(Visits!$S$2:$S$75,MATCH(29,Visits!$U$2:$U$75,0)),"")
A35: =IFERROR(INDEX(Visits!$B$2:$B$75,MATCH(30,Visits!$U$2:$U$75,0)),"") | B35: =IFERROR(INDEX(Visits!$A$2:$A$75,MATCH(30,Visits!$U$2:$U$75,0)),"") | C35: =IFERROR(INDEX(Visits!$C$2:$C$75,MATCH(30,Visits!$U$2:$U$75,0)),"") | D35: =IFERROR(INDEX(Visits!$D$2:$D$75,MATCH(30,Visits!$U$2:$U$75,0)),"") | E35: =IFERROR(INDEX(Visits!$Q$2:$Q$75,MATCH(30,Visits!$U$2:$U$75,0)),"") | F35: =IFERROR(INDEX(Visits!$R$2:$R$75,MATCH(30,Visits!$U$2:$U$75,0)),"") | G35: =IFERROR(INDEX(Visits!$S$2:$S$75,MATCH(30,Visits!$U$2:$U$75,0)),"")
A36: =IFERROR(INDEX(Visits!$B$2:$B$75,MATCH(31,Visits!$U$2:$U$75,0)),"") | B36: =IFERROR(INDEX(Visits!$A$2:$A$75,MATCH(31,Visits!$U$2:$U$75,0)),"") | C36: =IFERROR(INDEX(Visits!$C$2:$C$75,MATCH(31,Visits!$U$2:$U$75,0)),"") | D36: =IFERROR(INDEX(Visits!$D$2:$D$75,MATCH(31,Visits!$U$2:$U$75,0)),"") | E36: =IFERROR(INDEX(Visits!$Q$2:$Q$75,MATCH(31,Visits!$U$2:$U$75,0)),"") | F36: =IFERROR(INDEX(Visits!$R$2:$R$75,MATCH(31,Visits!$U$2:$U$75,0)),"") | G36: =IFERROR(INDEX(Visits!$S$2:$S$75,MATCH(31,Visits!$U$2:$U$75,0)),"")
A37: =IFERROR(INDEX(Visits!$B$2:$B$75,MATCH(32,Visits!$U$2:$U$75,0)),"") | B37: =IFERROR(INDEX(Visits!$A$2:$A$75,MATCH(32,Visits!$U$2:$U$75,0)),"") | C37: =IFERROR(INDEX(Visits!$C$2:$C$75,MATCH(32,Visits!$U$2:$U$75,0)),"") | D37: =IFERROR(INDEX(Visits!$D$2:$D$75,MATCH(32,Visits!$U$2:$U$75,0)),"") | E37: =IFERROR(INDEX(Visits!$Q$2:$Q$75,MATCH(32,Visits!$U$2:$U$75,0)),"") | F37: =IFERROR(INDEX(Visits!$R$2:$R$75,MATCH(32,Visits!$U$2:$U$75,0)),"") | G37: =IFERROR(INDEX(Visits!$S$2:$S$75,MATCH(32,Visits!$U$2:$U$75,0)),"")
A38: =IFERROR(INDEX(Visits!$B$2:$B$75,MATCH(33,Visits!$U$2:$U$75,0)),"") | B38: =IFERROR(INDEX(Visits!$A$2:$A$75,MATCH(33,Visits!$U$2:$U$75,0)),"") | C38: =IFERROR(INDEX(Visits!$C$2:$C$75,MATCH(33,Visits!$U$2:$U$75,0)),"") | D38: =IFERROR(INDEX(Visits!$D$2:$D$75,MATCH(33,Visits!$U$2:$U$75,0)),"") | E38: =IFERROR(INDEX(Visits!$Q$2:$Q$75,MATCH(33,Visits!$U$2:$U$75,0)),"") | F38: =IFERROR(INDEX(Visits!$R$2:$R$75,MATCH(33,Visits!$U$2:$U$75,0)),"") | G38: =IFERROR(INDEX(Visits!$S$2:$S$75,MATCH(33,Visits!$U$2:$U$75,0)),"")
A39: =IFERROR(INDEX(Visits!$B$2:$B$75,MATCH(34,Visits!$U$2:$U$75,0)),"") | B39: =IFERROR(INDEX(Visits!$A$2:$A$75,MATCH(34,Visits!$U$2:$U$75,0)),"") | C39: =IFERROR(INDEX(Visits!$C$2:$C$75,MATCH(34,Visits!$U$2:$U$75,0)),"") | D39: =IFERROR(INDEX(Visits!$D$2:$D$75,MATCH(34,Visits!$U$2:$U$75,0)),"") | E39: =IFERROR(INDEX(Visits!$Q$2:$Q$75,MATCH(34,Visits!$U$2:$U$75,0)),"") | F39: =IFERROR(INDEX(Visits!$R$2:$R$75,MATCH(34,Visits!$U$2:$U$75,0)),"") | G39: =IFERROR(INDEX(Visits!$S$2:$S$75,MATCH(34,Visits!$U$2:$U$75,0)),"")
A40: =IFERROR(INDEX(Visits!$B$2:$B$75,MATCH(35,Visits!$U$2:$U$75,0)),"") | B40: =IFERROR(INDEX(Visits!$A$2:$A$75,MATCH(35,Visits!$U$2:$U$75,0)),"") | C40: =IFERROR(INDEX(Visits!$C$2:$C$75,MATCH(35,Visits!$U$2:$U$75,0)),"") | D40: =IFERROR(INDEX(Visits!$D$2:$D$75,MATCH(35,Visits!$U$2:$U$75,0)),"") | E40: =IFERROR(INDEX(Visits!$Q$2:$Q$75,MATCH(35,Visits!$U$2:$U$75,0)),"") | F40: =IFERROR(INDEX(Visits!$R$2:$R$75,MATCH(35,Visits!$U$2:$U$75,0)),"") | G40: =IFERROR(INDEX(Visits!$S$2:$S$75,MATCH(35,Visits!$U$2:$U$75,0)),"")
A41: =IFERROR(INDEX(Visits!$B$2:$B$75,MATCH(36,Visits!$U$2:$U$75,0)),"") | B41: =IFERROR(INDEX(Visits!$A$2:$A$75,MATCH(36,Visits!$U$2:$U$75,0)),"") | C41: =IFERROR(INDEX(Visits!$C$2:$C$75,MATCH(36,Visits!$U$2:$U$75,0)),"") | D41: =IFERROR(INDEX(Visits!$D$2:$D$75,MATCH(36,Visits!$U$2:$U$75,0)),"") | E41: =IFERROR(INDEX(Visits!$Q$2:$Q$75,MATCH(36,Visits!$U$2:$U$75,0)),"") | F41: =IFERROR(INDEX(Visits!$R$2:$R$75,MATCH(36,Visits!$U$2:$U$75,0)),"") | G41: =IFERROR(INDEX(Visits!$S$2:$S$75,MATCH(36,Visits!$U$2:$U$75,0)),"")
A42: =IFERROR(INDEX(Visits!$B$2:$B$75,MATCH(37,Visits!$U$2:$U$75,0)),"") | B42: =IFERROR(INDEX(Visits!$A$2:$A$75,MATCH(37,Visits!$U$2:$U$75,0)),"") | C42: =IFERROR(INDEX(Visits!$C$2:$C$75,MATCH(37,Visits!$U$2:$U$75,0)),"") | D42: =IFERROR(INDEX(Visits!$D$2:$D$75,MATCH(37,Visits!$U$2:$U$75,0)),"") | E42: =IFERROR(INDEX(Visits!$Q$2:$Q$75,MATCH(37,Visits!$U$2:$U$75,0)),"") | F42: =IFERROR(INDEX(Visits!$R$2:$R$75,MATCH(37,Visits!$U$2:$U$75,0)),"") | G42: =IFERROR(INDEX(Visits!$S$2:$S$75,MATCH(37,Visits!$U$2:$U$75,0)),"")
A43: =IFERROR(INDEX(Visits!$B$2:$B$75,MATCH(38,Visits!$U$2:$U$75,0)),"") | B43: =IFERROR(INDEX(Visits!$A$2:$A$75,MATCH(38,Visits!$U$2:$U$75,0)),"") | C43: =IFERROR(INDEX(Visits!$C$2:$C$75,MATCH(38,Visits!$U$2:$U$75,0)),"") | D43: =IFERROR(INDEX(Visits!$D$2:$D$75,MATCH(38,Visits!$U$2:$U$75,0)),"") | E43: =IFERROR(INDEX(Visits!$Q$2:$Q$75,MATCH(38,Visits!$U$2:$U$75,0)),"") | F43: =IFERROR(INDEX(Visits!$R$2:$R$75,MATCH(38,Visits!$U$2:$U$75,0)),"") | G43: =IFERROR(INDEX(Visits!$S$2:$S$75,MATCH(38,Visits!$U$2:$U$75,0)),"")
A44: =IFERROR(INDEX(Visits!$B$2:$B$75,MATCH(39,Visits!$U$2:$U$75,0)),"") | B44: =IFERROR(INDEX(Visits!$A$2:$A$75,MATCH(39,Visits!$U$2:$U$75,0)),"") | C44: =IFERROR(INDEX(Visits!$C$2:$C$75,MATCH(39,Visits!$U$2:$U$75,0)),"") | D44: =IFERROR(INDEX(Visits!$D$2:$D$75,MATCH(39,Visits!$U$2:$U$75,0)),"") | E44: =IFERROR(INDEX(Visits!$Q$2:$Q$75,MATCH(39,Visits!$U$2:$U$75,0)),"") | F44: =IFERROR(INDEX(Visits!$R$2:$R$75,MATCH(39,Visits!$U$2:$U$75,0)),"") | G44: =IFERROR(INDEX(Visits!$S$2:$S$75,MATCH(39,Visits!$U$2:$U$75,0)),"")
A45: =IFERROR(INDEX(Visits!$B$2:$B$75,MATCH(40,Visits!$U$2:$U$75,0)),"") | B45: =IFERROR(INDEX(Visits!$A$2:$A$75,MATCH(40,Visits!$U$2:$U$75,0)),"") | C45: =IFERROR(INDEX(Visits!$C$2:$C$75,MATCH(40,Visits!$U$2:$U$75,0)),"") | D45: =IFERROR(INDEX(Visits!$D$2:$D$75,MATCH(40,Visits!$U$2:$U$75,0)),"") | E45: =IFERROR(INDEX(Visits!$Q$2:$Q$75,MATCH(40,Visits!$U$2:$U$75,0)),"") | F45: =IFERROR(INDEX(Visits!$R$2:$R$75,MATCH(40,Visits!$U$2:$U$75,0)),"") | G45: =IFERROR(INDEX(Visits!$S$2:$S$75,MATCH(40,Visits!$U$2:$U$75,0)),"")
A46: =IFERROR(INDEX(Visits!$B$2:$B$75,MATCH(41,Visits!$U$2:$U$75,0)),"") | B46: =IFERROR(INDEX(Visits!$A$2:$A$75,MATCH(41,Visits!$U$2:$U$75,0)),"") | C46: =IFERROR(INDEX(Visits!$C$2:$C$75,MATCH(41,Visits!$U$2:$U$75,0)),"") | D46: =IFERROR(INDEX(Visits!$D$2:$D$75,MATCH(41,Visits!$U$2:$U$75,0)),"") | E46: =IFERROR(INDEX(Visits!$Q$2:$Q$75,MATCH(41,Visits!$U$2:$U$75,0)),"") | F46: =IFERROR(INDEX(Visits!$R$2:$R$75,MATCH(41,Visits!$U$2:$U$75,0)),"") | G46: =IFERROR(INDEX(Visits!$S$2:$S$75,MATCH(41,Visits!$U$2:$U$75,0)),"")
A47: =IFERROR(INDEX(Visits!$B$2:$B$75,MATCH(42,Visits!$U$2:$U$75,0)),"") | B47: =IFERROR(INDEX(Visits!$A$2:$A$75,MATCH(42,Visits!$U$2:$U$75,0)),"") | C47: =IFERROR(INDEX(Visits!$C$2:$C$75,MATCH(42,Visits!$U$2:$U$75,0)),"") | D47: =IFERROR(INDEX(Visits!$D$2:$D$75,MATCH(42,Visits!$U$2:$U$75,0)),"") | E47: =IFERROR(INDEX(Visits!$Q$2:$Q$75,MATCH(42,Visits!$U$2:$U$75,0)),"") | F47: =IFERROR(INDEX(Visits!$R$2:$R$75,MATCH(42,Visits!$U$2:$U$75,0)),"") | G47: =IFERROR(INDEX(Visits!$S$2:$S$75,MATCH(42,Visits!$U$2:$U$75,0)),"")
A48: =IFERROR(INDEX(Visits!$B$2:$B$75,MATCH(43,Visits!$U$2:$U$75,0)),"") | B48: =IFERROR(INDEX(Visits!$A$2:$A$75,MATCH(43,Visits!$U$2:$U$75,0)),"") | C48: =IFERROR(INDEX(Visits!$C$2:$C$75,MATCH(43,Visits!$U$2:$U$75,0)),"") | D48: =IFERROR(INDEX(Visits!$D$2:$D$75,MATCH(43,Visits!$U$2:$U$75,0)),"") | E48: =IFERROR(INDEX(Visits!$Q$2:$Q$75,MATCH(43,Visits!$U$2:$U$75,0)),"") | F48: =IFERROR(INDEX(Visits!$R$2:$R$75,MATCH(43,Visits!$U$2:$U$75,0)),"") | G48: =IFERROR(INDEX(Visits!$S$2:$S$75,MATCH(43,Visits!$U$2:$U$75,0)),"")
A49: =IFERROR(INDEX(Visits!$B$2:$B$75,MATCH(44,Visits!$U$2:$U$75,0)),"") | B49: =IFERROR(INDEX(Visits!$A$2:$A$75,MATCH(44,Visits!$U$2:$U$75,0)),"") | C49: =IFERROR(INDEX(Visits!$C$2:$C$75,MATCH(44,Visits!$U$2:$U$75,0)),"") | D49: =IFERROR(INDEX(Visits!$D$2:$D$75,MATCH(44,Visits!$U$2:$U$75,0)),"") | E49: =IFERROR(INDEX(Visits!$Q$2:$Q$75,MATCH(44,Visits!$U$2:$U$75,0)),"") | F49: =IFERROR(INDEX(Visits!$R$2:$R$75,MATCH(44,Visits!$U$2:$U$75,0)),"") | G49: =IFERROR(INDEX(Visits!$S$2:$S$75,MATCH(44,Visits!$U$2:$U$75,0)),"")
A50: =IFERROR(INDEX(Visits!$B$2:$B$75,MATCH(45,Visits!$U$2:$U$75,0)),"") | B50: =IFERROR(INDEX(Visits!$A$2:$A$75,MATCH(45,Visits!$U$2:$U$75,0)),"") | C50: =IFERROR(INDEX(Visits!$C$2:$C$75,MATCH(45,Visits!$U$2:$U$75,0)),"") | D50: =IFERROR(INDEX(Visits!$D$2:$D$75,MATCH(45,Visits!$U$2:$U$75,0)),"") | E50: =IFERROR(INDEX(Visits!$Q$2:$Q$75,MATCH(45,Visits!$U$2:$U$75,0)),"") | F50: =IFERROR(INDEX(Visits!$R$2:$R$75,MATCH(45,Visits!$U$2:$U$75,0)),"") | G50: =IFERROR(INDEX(Visits!$S$2:$S$75,MATCH(45,Visits!$U$2:$U$75,0)),"")
A51: =IFERROR(INDEX(Visits!$B$2:$B$75,MATCH(46,Visits!$U$2:$U$75,0)),"") | B51: =IFERROR(INDEX(Visits!$A$2:$A$75,MATCH(46,Visits!$U$2:$U$75,0)),"") | C51: =IFERROR(INDEX(Visits!$C$2:$C$75,MATCH(46,Visits!$U$2:$U$75,0)),"") | D51: =IFERROR(INDEX(Visits!$D$2:$D$75,MATCH(46,Visits!$U$2:$U$75,0)),"") | E51: =IFERROR(INDEX(Visits!$Q$2:$Q$75,MATCH(46,Visits!$U$2:$U$75,0)),"") | F51: =IFERROR(INDEX(Visits!$R$2:$R$75,MATCH(46,Visits!$U$2:$U$75,0)),"") | G51: =IFERROR(INDEX(Visits!$S$2:$S$75,MATCH(46,Visits!$U$2:$U$75,0)),"")
A52: =IFERROR(INDEX(Visits!$B$2:$B$75,MATCH(47,Visits!$U$2:$U$75,0)),"") | B52: =IFERROR(INDEX(Visits!$A$2:$A$75,MATCH(47,Visits!$U$2:$U$75,0)),"") | C52: =IFERROR(INDEX(Visits!$C$2:$C$75,MATCH(47,Visits!$U$2:$U$75,0)),"") | D52: =IFERROR(INDEX(Visits!$D$2:$D$75,MATCH(47,Visits!$U$2:$U$75,0)),"") | E52: =IFERROR(INDEX(Visits!$Q$2:$Q$75,MATCH(47,Visits!$U$2:$U$75,0)),"") | F52: =IFERROR(INDEX(Visits!$R$2:$R$75,MATCH(47,Visits!$U$2:$U$75,0)),"") | G52: =IFERROR(INDEX(Visits!$S$2:$S$75,MATCH(47,Visits!$U$2:$U$75,0)),"")
A53: =IFERROR(INDEX(Visits!$B$2:$B$75,MATCH(48,Visits!$U$2:$U$75,0)),"") | B53: =IFERROR(INDEX(Visits!$A$2:$A$75,MATCH(48,Visits!$U$2:$U$75,0)),"") | C53: =IFERROR(INDEX(Visits!$C$2:$C$75,MATCH(48,Visits!$U$2:$U$75,0)),"") | D53: =IFERROR(INDEX(Visits!$D$2:$D$75,MATCH(48,Visits!$U$2:$U$75,0)),"") | E53: =IFERROR(INDEX(Visits!$Q$2:$Q$75,MATCH(48,Visits!$U$2:$U$75,0)),"") | F53: =IFERROR(INDEX(Visits!$R$2:$R$75,MATCH(48,Visits!$U$2:$U$75,0)),"") | G53: =IFERROR(INDEX(Visits!$S$2:$S$75,MATCH(48,Visits!$U$2:$U$75,0)),"")
A54: =IFERROR(INDEX(Visits!$B$2:$B$75,MATCH(49,Visits!$U$2:$U$75,0)),"") | B54: =IFERROR(INDEX(Visits!$A$2:$A$75,MATCH(49,Visits!$U$2:$U$75,0)),"") | C54: =IFERROR(INDEX(Visits!$C$2:$C$75,MATCH(49,Visits!$U$2:$U$75,0)),"") | D54: =IFERROR(INDEX(Visits!$D$2:$D$75,MATCH(49,Visits!$U$2:$U$75,0)),"") | E54: =IFERROR(INDEX(Visits!$Q$2:$Q$75,MATCH(49,Visits!$U$2:$U$75,0)),"") | F54: =IFERROR(INDEX(Visits!$R$2:$R$75,MATCH(49,Visits!$U$2:$U$75,0)),"") | G54: =IFERROR(INDEX(Visits!$S$2:$S$75,MATCH(49,Visits!$U$2:$U$75,0)),"")
A55: =IFERROR(INDEX(Visits!$B$2:$B$75,MATCH(50,Visits!$U$2:$U$75,0)),"") | B55: =IFERROR(INDEX(Visits!$A$2:$A$75,MATCH(50,Visits!$U$2:$U$75,0)),"") | C55: =IFERROR(INDEX(Visits!$C$2:$C$75,MATCH(50,Visits!$U$2:$U$75,0)),"") | D55: =IFERROR(INDEX(Visits!$D$2:$D$75,MATCH(50,Visits!$U$2:$U$75,0)),"") | E55: =IFERROR(INDEX(Visits!$Q$2:$Q$75,MATCH(50,Visits!$U$2:$U$75,0)),"") | F55: =IFERROR(INDEX(Visits!$R$2:$R$75,MATCH(50,Visits!$U$2:$U$75,0)),"") | G55: =IFERROR(INDEX(Visits!$S$2:$S$75,MATCH(50,Visits!$U$2:$U$75,0)),"")
A56: =IFERROR(INDEX(Visits!$B$2:$B$75,MATCH(51,Visits!$U$2:$U$75,0)),"") | B56: =IFERROR(INDEX(Visits!$A$2:$A$75,MATCH(51,Visits!$U$2:$U$75,0)),"") | C56: =IFERROR(INDEX(Visits!$C$2:$C$75,MATCH(51,Visits!$U$2:$U$75,0)),"") | D56: =IFERROR(INDEX(Visits!$D$2:$D$75,MATCH(51,Visits!$U$2:$U$75,0)),"") | E56: =IFERROR(INDEX(Visits!$Q$2:$Q$75,MATCH(51,Visits!$U$2:$U$75,0)),"") | F56: =IFERROR(INDEX(Visits!$R$2:$R$75,MATCH(51,Visits!$U$2:$U$75,0)),"") | G56: =IFERROR(INDEX(Visits!$S$2:$S$75,MATCH(51,Visits!$U$2:$U$75,0)),"")
A57: =IFERROR(INDEX(Visits!$B$2:$B$75,MATCH(52,Visits!$U$2:$U$75,0)),"") | B57: =IFERROR(INDEX(Visits!$A$2:$A$75,MATCH(52,Visits!$U$2:$U$75,0)),"") | C57: =IFERROR(INDEX(Visits!$C$2:$C$75,MATCH(52,Visits!$U$2:$U$75,0)),"") | D57: =IFERROR(INDEX(Visits!$D$2:$D$75,MATCH(52,Visits!$U$2:$U$75,0)),"") | E57: =IFERROR(INDEX(Visits!$Q$2:$Q$75,MATCH(52,Visits!$U$2:$U$75,0)),"") | F57: =IFERROR(INDEX(Visits!$R$2:$R$75,MATCH(52,Visits!$U$2:$U$75,0)),"") | G57: =IFERROR(INDEX(Visits!$S$2:$S$75,MATCH(52,Visits!$U$2:$U$75,0)),"")
A58: =IFERROR(INDEX(Visits!$B$2:$B$75,MATCH(53,Visits!$U$2:$U$75,0)),"") | B58: =IFERROR(INDEX(Visits!$A$2:$A$75,MATCH(53,Visits!$U$2:$U$75,0)),"") | C58: =IFERROR(INDEX(Visits!$C$2:$C$75,MATCH(53,Visits!$U$2:$U$75,0)),"") | D58: =IFERROR(INDEX(Visits!$D$2:$D$75,MATCH(53,Visits!$U$2:$U$75,0)),"") | E58: =IFERROR(INDEX(Visits!$Q$2:$Q$75,MATCH(53,Visits!$U$2:$U$75,0)),"") | F58: =IFERROR(INDEX(Visits!$R$2:$R$75,MATCH(53,Visits!$U$2:$U$75,0)),"") | G58: =IFERROR(INDEX(Visits!$S$2:$S$75,MATCH(53,Visits!$U$2:$U$75,0)),"")
A59: =IFERROR(INDEX(Visits!$B$2:$B$75,MATCH(54,Visits!$U$2:$U$75,0)),"") | B59: =IFERROR(INDEX(Visits!$A$2:$A$75,MATCH(54,Visits!$U$2:$U$75,0)),"") | C59: =IFERROR(INDEX(Visits!$C$2:$C$75,MATCH(54,Visits!$U$2:$U$75,0)),"") | D59: =IFERROR(INDEX(Visits!$D$2:$D$75,MATCH(54,Visits!$U$2:$U$75,0)),"") | E59: =IFERROR(INDEX(Visits!$Q$2:$Q$75,MATCH(54,Visits!$U$2:$U$75,0)),"") | F59: =IFERROR(INDEX(Visits!$R$2:$R$75,MATCH(54,Visits!$U$2:$U$75,0)),"") | G59: =IFERROR(INDEX(Visits!$S$2:$S$75,MATCH(54,Visits!$U$2:$U$75,0)),"")
A60: =IFERROR(INDEX(Visits!$B$2:$B$75,MATCH(55,Visits!$U$2:$U$75,0)),"") | B60: =IFERROR(INDEX(Visits!$A$2:$A$75,MATCH(55,Visits!$U$2:$U$75,0)),"") | C60: =IFERROR(INDEX(Visits!$C$2:$C$75,MATCH(55,Visits!$U$2:$U$75,0)),"") | D60: =IFERROR(INDEX(Visits!$D$2:$D$75,MATCH(55,Visits!$U$2:$U$75,0)),"") | E60: =IFERROR(INDEX(Visits!$Q$2:$Q$75,MATCH(55,Visits!$U$2:$U$75,0)),"") | F60: =IFERROR(INDEX(Visits!$R$2:$R$75,MATCH(55,Visits!$U$2:$U$75,0)),"") | G60: =IFERROR(INDEX(Visits!$S$2:$S$75,MATCH(55,Visits!$U$2:$U$75,0)),"")
A61: =IFERROR(INDEX(Visits!$B$2:$B$75,MATCH(56,Visits!$U$2:$U$75,0)),"") | B61: =IFERROR(INDEX(Visits!$A$2:$A$75,MATCH(56,Visits!$U$2:$U$75,0)),"") | C61: =IFERROR(INDEX(Visits!$C$2:$C$75,MATCH(56,Visits!$U$2:$U$75,0)),"") | D61: =IFERROR(INDEX(Visits!$D$2:$D$75,MATCH(56,Visits!$U$2:$U$75,0)),"") | E61: =IFERROR(INDEX(Visits!$Q$2:$Q$75,MATCH(56,Visits!$U$2:$U$75,0)),"") | F61: =IFERROR(INDEX(Visits!$R$2:$R$75,MATCH(56,Visits!$U$2:$U$75,0)),"") | G61: =IFERROR(INDEX(Visits!$S$2:$S$75,MATCH(56,Visits!$U$2:$U$75,0)),"")
A62: =IFERROR(INDEX(Visits!$B$2:$B$75,MATCH(57,Visits!$U$2:$U$75,0)),"") | B62: =IFERROR(INDEX(Visits!$A$2:$A$75,MATCH(57,Visits!$U$2:$U$75,0)),"") | C62: =IFERROR(INDEX(Visits!$C$2:$C$75,MATCH(57,Visits!$U$2:$U$75,0)),"") | D62: =IFERROR(INDEX(Visits!$D$2:$D$75,MATCH(57,Visits!$U$2:$U$75,0)),"") | E62: =IFERROR(INDEX(Visits!$Q$2:$Q$75,MATCH(57,Visits!$U$2:$U$75,0)),"") | F62: =IFERROR(INDEX(Visits!$R$2:$R$75,MATCH(57,Visits!$U$2:$U$75,0)),"") | G62: =IFERROR(INDEX(Visits!$S$2:$S$75,MATCH(57,Visits!$U$2:$U$75,0)),"")
A63: =IFERROR(INDEX(Visits!$B$2:$B$75,MATCH(58,Visits!$U$2:$U$75,0)),"") | B63: =IFERROR(INDEX(Visits!$A$2:$A$75,MATCH(58,Visits!$U$2:$U$75,0)),"") | C63: =IFERROR(INDEX(Visits!$C$2:$C$75,MATCH(58,Visits!$U$2:$U$75,0)),"") | D63: =IFERROR(INDEX(Visits!$D$2:$D$75,MATCH(58,Visits!$U$2:$U$75,0)),"") | E63: =IFERROR(INDEX(Visits!$Q$2:$Q$75,MATCH(58,Visits!$U$2:$U$75,0)),"") | F63: =IFERROR(INDEX(Visits!$R$2:$R$75,MATCH(58,Visits!$U$2:$U$75,0)),"") | G63: =IFERROR(INDEX(Visits!$S$2:$S$75,MATCH(58,Visits!$U$2:$U$75,0)),"")
A64: =IFERROR(INDEX(Visits!$B$2:$B$75,MATCH(59,Visits!$U$2:$U$75,0)),"") | B64: =IFERROR(INDEX(Visits!$A$2:$A$75,MATCH(59,Visits!$U$2:$U$75,0)),"") | C64: =IFERROR(INDEX(Visits!$C$2:$C$75,MATCH(59,Visits!$U$2:$U$75,0)),"") | D64: =IFERROR(INDEX(Visits!$D$2:$D$75,MATCH(59,Visits!$U$2:$U$75,0)),"") | E64: =IFERROR(INDEX(Visits!$Q$2:$Q$75,MATCH(59,Visits!$U$2:$U$75,0)),"") | F64: =IFERROR(INDEX(Visits!$R$2:$R$75,MATCH(59,Visits!$U$2:$U$75,0)),"") | G64: =IFERROR(INDEX(Visits!$S$2:$S$75,MATCH(59,Visits!$U$2:$U$75,0)),"")
A65: =IFERROR(INDEX(Visits!$B$2:$B$75,MATCH(60,Visits!$U$2:$U$75,0)),"") | B65: =IFERROR(INDEX(Visits!$A$2:$A$75,MATCH(60,Visits!$U$2:$U$75,0)),"") | C65: =IFERROR(INDEX(Visits!$C$2:$C$75,MATCH(60,Visits!$U$2:$U$75,0)),"") | D65: =IFERROR(INDEX(Visits!$D$2:$D$75,MATCH(60,Visits!$U$2:$U$75,0)),"") | E65: =IFERROR(INDEX(Visits!$Q$2:$Q$75,MATCH(60,Visits!$U$2:$U$75,0)),"") | F65: =IFERROR(INDEX(Visits!$R$2:$R$75,MATCH(60,Visits!$U$2:$U$75,0)),"") | G65: =IFERROR(INDEX(Visits!$S$2:$S$75,MATCH(60,Visits!$U$2:$U$75,0)),"")
A66: =IFERROR(INDEX(Visits!$B$2:$B$75,MATCH(61,Visits!$U$2:$U$75,0)),"") | B66: =IFERROR(INDEX(Visits!$A$2:$A$75,MATCH(61,Visits!$U$2:$U$75,0)),"") | C66: =IFERROR(INDEX(Visits!$C$2:$C$75,MATCH(61,Visits!$U$2:$U$75,0)),"") | D66: =IFERROR(INDEX(Visits!$D$2:$D$75,MATCH(61,Visits!$U$2:$U$75,0)),"") | E66: =IFERROR(INDEX(Visits!$Q$2:$Q$75,MATCH(61,Visits!$U$2:$U$75,0)),"") | F66: =IFERROR(INDEX(Visits!$R$2:$R$75,MATCH(61,Visits!$U$2:$U$75,0)),"") | G66: =IFERROR(INDEX(Visits!$S$2:$S$75,MATCH(61,Visits!$U$2:$U$75,0)),"")
A67: =IFERROR(INDEX(Visits!$B$2:$B$75,MATCH(62,Visits!$U$2:$U$75,0)),"") | B67: =IFERROR(INDEX(Visits!$A$2:$A$75,MATCH(62,Visits!$U$2:$U$75,0)),"") | C67: =IFERROR(INDEX(Visits!$C$2:$C$75,MATCH(62,Visits!$U$2:$U$75,0)),"") | D67: =IFERROR(INDEX(Visits!$D$2:$D$75,MATCH(62,Visits!$U$2:$U$75,0)),"") | E67: =IFERROR(INDEX(Visits!$Q$2:$Q$75,MATCH(62,Visits!$U$2:$U$75,0)),"") | F67: =IFERROR(INDEX(Visits!$R$2:$R$75,MATCH(62,Visits!$U$2:$U$75,0)),"") | G67: =IFERROR(INDEX(Visits!$S$2:$S$75,MATCH(62,Visits!$U$2:$U$75,0)),"")
A68: =IFERROR(INDEX(Visits!$B$2:$B$75,MATCH(63,Visits!$U$2:$U$75,0)),"") | B68: =IFERROR(INDEX(Visits!$A$2:$A$75,MATCH(63,Visits!$U$2:$U$75,0)),"") | C68: =IFERROR(INDEX(Visits!$C$2:$C$75,MATCH(63,Visits!$U$2:$U$75,0)),"") | D68: =IFERROR(INDEX(Visits!$D$2:$D$75,MATCH(63,Visits!$U$2:$U$75,0)),"") | E68: =IFERROR(INDEX(Visits!$Q$2:$Q$75,MATCH(63,Visits!$U$2:$U$75,0)),"") | F68: =IFERROR(INDEX(Visits!$R$2:$R$75,MATCH(63,Visits!$U$2:$U$75,0)),"") | G68: =IFERROR(INDEX(Visits!$S$2:$S$75,MATCH(63,Visits!$U$2:$U$75,0)),"")
A69: =IFERROR(INDEX(Visits!$B$2:$B$75,MATCH(64,Visits!$U$2:$U$75,0)),"") | B69: =IFERROR(INDEX(Visits!$A$2:$A$75,MATCH(64,Visits!$U$2:$U$75,0)),"") | C69: =IFERROR(INDEX(Visits!$C$2:$C$75,MATCH(64,Visits!$U$2:$U$75,0)),"") | D69: =IFERROR(INDEX(Visits!$D$2:$D$75,MATCH(64,Visits!$U$2:$U$75,0)),"") | E69: =IFERROR(INDEX(Visits!$Q$2:$Q$75,MATCH(64,Visits!$U$2:$U$75,0)),"") | F69: =IFERROR(INDEX(Visits!$R$2:$R$75,MATCH(64,Visits!$U$2:$U$75,0)),"") | G69: =IFERROR(INDEX(Visits!$S$2:$S$75,MATCH(64,Visits!$U$2:$U$75,0)),"")
A70: =IFERROR(INDEX(Visits!$B$2:$B$75,MATCH(65,Visits!$U$2:$U$75,0)),"") | B70: =IFERROR(INDEX(Visits!$A$2:$A$75,MATCH(65,Visits!$U$2:$U$75,0)),"") | C70: =IFERROR(INDEX(Visits!$C$2:$C$75,MATCH(65,Visits!$U$2:$U$75,0)),"") | D70: =IFERROR(INDEX(Visits!$D$2:$D$75,MATCH(65,Visits!$U$2:$U$75,0)),"") | E70: =IFERROR(INDEX(Visits!$Q$2:$Q$75,MATCH(65,Visits!$U$2:$U$75,0)),"") | F70: =IFERROR(INDEX(Visits!$R$2:$R$75,MATCH(65,Visits!$U$2:$U$75,0)),"") | G70: =IFERROR(INDEX(Visits!$S$2:$S$75,MATCH(65,Visits!$U$2:$U$75,0)),"")
A71: =IFERROR(INDEX(Visits!$B$2:$B$75,MATCH(66,Visits!$U$2:$U$75,0)),"") | B71: =IFERROR(INDEX(Visits!$A$2:$A$75,MATCH(66,Visits!$U$2:$U$75,0)),"") | C71: =IFERROR(INDEX(Visits!$C$2:$C$75,MATCH(66,Visits!$U$2:$U$75,0)),"") | D71: =IFERROR(INDEX(Visits!$D$2:$D$75,MATCH(66,Visits!$U$2:$U$75,0)),"") | E71: =IFERROR(INDEX(Visits!$Q$2:$Q$75,MATCH(66,Visits!$U$2:$U$75,0)),"") | F71: =IFERROR(INDEX(Visits!$R$2:$R$75,MATCH(66,Visits!$U$2:$U$75,0)),"") | G71: =IFERROR(INDEX(Visits!$S$2:$S$75,MATCH(66,Visits!$U$2:$U$75,0)),"")
A72: =IFERROR(INDEX(Visits!$B$2:$B$75,MATCH(67,Visits!$U$2:$U$75,0)),"") | B72: =IFERROR(INDEX(Visits!$A$2:$A$75,MATCH(67,Visits!$U$2:$U$75,0)),"") | C72: =IFERROR(INDEX(Visits!$C$2:$C$75,MATCH(67,Visits!$U$2:$U$75,0)),"") | D72: =IFERROR(INDEX(Visits!$D$2:$D$75,MATCH(67,Visits!$U$2:$U$75,0)),"") | E72: =IFERROR(INDEX(Visits!$Q$2:$Q$75,MATCH(67,Visits!$U$2:$U$75,0)),"") | F72: =IFERROR(INDEX(Visits!$R$2:$R$75,MATCH(67,Visits!$U$2:$U$75,0)),"") | G72: =IFERROR(INDEX(Visits!$S$2:$S$75,MATCH(67,Visits!$U$2:$U$75,0)),"")
A73: =IFERROR(INDEX(Visits!$B$2:$B$75,MATCH(68,Visits!$U$2:$U$75,0)),"") | B73: =IFERROR(INDEX(Visits!$A$2:$A$75,MATCH(68,Visits!$U$2:$U$75,0)),"") | C73: =IFERROR(INDEX(Visits!$C$2:$C$75,MATCH(68,Visits!$U$2:$U$75,0)),"") | D73: =IFERROR(INDEX(Visits!$D$2:$D$75,MATCH(68,Visits!$U$2:$U$75,0)),"") | E73: =IFERROR(INDEX(Visits!$Q$2:$Q$75,MATCH(68,Visits!$U$2:$U$75,0)),"") | F73: =IFERROR(INDEX(Visits!$R$2:$R$75,MATCH(68,Visits!$U$2:$U$75,0)),"") | G73: =IFERROR(INDEX(Visits!$S$2:$S$75,MATCH(68,Visits!$U$2:$U$75,0)),"")
A74: =IFERROR(INDEX(Visits!$B$2:$B$75,MATCH(69,Visits!$U$2:$U$75,0)),"") | B74: =IFERROR(INDEX(Visits!$A$2:$A$75,MATCH(69,Visits!$U$2:$U$75,0)),"") | C74: =IFERROR(INDEX(Visits!$C$2:$C$75,MATCH(69,Visits!$U$2:$U$75,0)),"") | D74: =IFERROR(INDEX(Visits!$D$2:$D$75,MATCH(69,Visits!$U$2:$U$75,0)),"") | E74: =IFERROR(INDEX(Visits!$Q$2:$Q$75,MATCH(69,Visits!$U$2:$U$75,0)),"") | F74: =IFERROR(INDEX(Visits!$R$2:$R$75,MATCH(69,Visits!$U$2:$U$75,0)),"") | G74: =IFERROR(INDEX(Visits!$S$2:$S$75,MATCH(69,Visits!$U$2:$U$75,0)),"")
A75: =IFERROR(INDEX(Visits!$B$2:$B$75,MATCH(70,Visits!$U$2:$U$75,0)),"") | B75: =IFERROR(INDEX(Visits!$A$2:$A$75,MATCH(70,Visits!$U$2:$U$75,0)),"") | C75: =IFERROR(INDEX(Visits!$C$2:$C$75,MATCH(70,Visits!$U$2:$U$75,0)),"") | D75: =IFERROR(INDEX(Visits!$D$2:$D$75,MATCH(70,Visits!$U$2:$U$75,0)),"") | E75: =IFERROR(INDEX(Visits!$Q$2:$Q$75,MATCH(70,Visits!$U$2:$U$75,0)),"") | F75: =IFERROR(INDEX(Visits!$R$2:$R$75,MATCH(70,Visits!$U$2:$U$75,0)),"") | G75: =IFERROR(INDEX(Visits!$S$2:$S$75,MATCH(70,Visits!$U$2:$U$75,0)),"")
A76: =IFERROR(INDEX(Visits!$B$2:$B$75,MATCH(71,Visits!$U$2:$U$75,0)),"") | B76: =IFERROR(INDEX(Visits!$A$2:$A$75,MATCH(71,Visits!$U$2:$U$75,0)),"") | C76: =IFERROR(INDEX(Visits!$C$2:$C$75,MATCH(71,Visits!$U$2:$U$75,0)),"") | D76: =IFERROR(INDEX(Visits!$D$2:$D$75,MATCH(71,Visits!$U$2:$U$75,0)),"") | E76: =IFERROR(INDEX(Visits!$Q$2:$Q$75,MATCH(71,Visits!$U$2:$U$75,0)),"") | F76: =IFERROR(INDEX(Visits!$R$2:$R$75,MATCH(71,Visits!$U$2:$U$75,0)),"") | G76: =IFERROR(INDEX(Visits!$S$2:$S$75,MATCH(71,Visits!$U$2:$U$75,0)),"")
A77: =IFERROR(INDEX(Visits!$B$2:$B$75,MATCH(72,Visits!$U$2:$U$75,0)),"") | B77: =IFERROR(INDEX(Visits!$A$2:$A$75,MATCH(72,Visits!$U$2:$U$75,0)),"") | C77: =IFERROR(INDEX(Visits!$C$2:$C$75,MATCH(72,Visits!$U$2:$U$75,0)),"") | D77: =IFERROR(INDEX(Visits!$D$2:$D$75,MATCH(72,Visits!$U$2:$U$75,0)),"") | E77: =IFERROR(INDEX(Visits!$Q$2:$Q$75,MATCH(72,Visits!$U$2:$U$75,0)),"") | F77: =IFERROR(INDEX(Visits!$R$2:$R$75,MATCH(72,Visits!$U$2:$U$75,0)),"") | G77: =IFERROR(INDEX(Visits!$S$2:$S$75,MATCH(72,Visits!$U$2:$U$75,0)),"")
A78: =IFERROR(INDEX(Visits!$B$2:$B$75,MATCH(73,Visits!$U$2:$U$75,0)),"") | B78: =IFERROR(INDEX(Visits!$A$2:$A$75,MATCH(73,Visits!$U$2:$U$75,0)),"") | C78: =IFERROR(INDEX(Visits!$C$2:$C$75,MATCH(73,Visits!$U$2:$U$75,0)),"") | D78: =IFERROR(INDEX(Visits!$D$2:$D$75,MATCH(73,Visits!$U$2:$U$75,0)),"") | E78: =IFERROR(INDEX(Visits!$Q$2:$Q$75,MATCH(73,Visits!$U$2:$U$75,0)),"") | F78: =IFERROR(INDEX(Visits!$R$2:$R$75,MATCH(73,Visits!$U$2:$U$75,0)),"") | G78: =IFERROR(INDEX(Visits!$S$2:$S$75,MATCH(73,Visits!$U$2:$U$75,0)),"")
A79: =IFERROR(INDEX(Visits!$B$2:$B$75,MATCH(74,Visits!$U$2:$U$75,0)),"") | B79: =IFERROR(INDEX(Visits!$A$2:$A$75,MATCH(74,Visits!$U$2:$U$75,0)),"") | C79: =IFERROR(INDEX(Visits!$C$2:$C$75,MATCH(74,Visits!$U$2:$U$75,0)),"") | D79: =IFERROR(INDEX(Visits!$D$2:$D$75,MATCH(74,Visits!$U$2:$U$75,0)),"") | E79: =IFERROR(INDEX(Visits!$Q$2:$Q$75,MATCH(74,Visits!$U$2:$U$75,0)),"") | F79: =IFERROR(INDEX(Visits!$R$2:$R$75,MATCH(74,Visits!$U$2:$U$75,0)),"") | G79: =IFERROR(INDEX(Visits!$S$2:$S$75,MATCH(74,Visits!$U$2:$U$75,0)),"")

Sheet Visits
A1: Manager | B1: Centre | C1: Program | D1: Date | E1: DataCheck_AW | F1: DataCheck_NI | G1: DataCheck_NA | H1: InfraCheck_AW | I1: InfraCheck_NI | J1: InfraCheck_NA | K1: ProcessCheck_AW | L1: ProcessCheck_NI | M1: ProcessCheck_NA | N1: AspirantInt_AW | O1: AspirantInt_NI | P1: AspirantInt_NA | Q1: Q_Bottleneck | R1: Q_PlacementAction | S1: Q_BatchOnTimeAction | T1: MatchFlag | U1: MatchRank
A2: Phani | B2: Vijayanagaram | C2: Grow Youth | D2: 2026-07-02 | E2: 7 | F2: 0 | G2: 1 | H2: 4 | I2: 3 | J2: 1 | K2: 11 | L2: 4 | M2: 7 | N2: 10 | O2: 0 | P2: 1 | Q2: Sent old laptops to HO, and arranged repairing of counseling room chairs. | R2: I will share employer leads of Vizag | S2: I have provided SIP team support and 18 students enrolled in present batch | T2: =IF(AND(OR(Dashboard!$B$5="All Managers",A2=Dashboard!$B$5),OR(Dashboard!$E$5="All Centres",B2=Dashboard!$E$5)),1,0) | U2: =IF(T2=1,COUNTIF($T$2:T2,1),"")
A3: S Jakir | B3: Bommanahalli | C3: GROW Youth | D3: 2026-07-02 | E3: 6 | F3: 2 | G3: 0 | H3: 4 | I3: 2 | J3: 2 | K3: 14 | L3: 3 | M3: 5 | N3: 9 | O3: 0 | P3: 2 | Q3: Conducted a focused discussion with the new trainer, Mrs. Harshadha, to understand her experience in handling the first batch and the reasons for the lower skill shift outcomes. Also reviewed her approach to managing the current batch. Provided guidance on key processes to be followed, shared relevant insights and best practices, and encouraged her by appreciating her efforts and the good work she has been doing. | R3: Aspirant mapping with quality employers and exclusive job drives with reputed employers have been missing over the last three months. I need to reinforce these activities and ensure their consistent implementation going forward. | S3: Referrals need to improve . Need to discuss with Trainers and guide them | T3: =IF(AND(OR(Dashboard!$B$5="All Managers",A3=Dashboard!$B$5),OR(Dashboard!$E$5="All Centres",B3=Dashboard!$E$5)),1,0) | U3: =IF(T3=1,COUNTIF($T$2:T3,1),"")
A4: S Jakir | B4: Hoskote | C4: HQHCS | D4: 2026-07-03 | E4: 8 | F4: 0 | G4: 0 | H4: 6 | I4: 2 | J4: 0 | K4: 17 | L4: 2 | M4: 3 | N4: 10 | O4: 0 | P4: 1 | Q4: Visited the PG facility, had lunch, and held a discussion with the PG management team. They were instructed to ensure the provision of quality food and to maintain better cleanliness standards within the premises. | R4: Need to share employer new employer leads | S4: CA hiring has to close ( interview forms shared for approval ) & complete CA induction training soon after the onboarding . | T4: =IF(AND(OR(Dashboard!$B$5="All Managers",A4=Dashboard!$B$5),OR(Dashboard!$E$5="All Centres",B4=Dashboard!$E$5)),1,0) | U4: =IF(T4=1,COUNTIF($T$2:T4,1),"")
A5: Raghavender Rao | B5: Karimnagar | C5: Grow-Green-Solar | D5: 2026-07-01 | E5: 8 | F5: 0 | G5: 0 | H5: 5 | I5: 3 | J5: 0 | K5: 20 | L5: 0 | M5: 2 | N5: 11 | O5: 0 | P5: 0 | Q5: The early placement details are pending and require immediate approval. During the visit, I verified all aspirants through video calls and obtained approval from the COO. A total of 17 aspirants have been verified and approved. | R5: The center is following a well-structured placement plan after the training and assessment process. With my continuous support, the team has successfully placed aspirants in the solar industry, ensuring better employment opportunities and placement outcomes. | S5: I had already suggested that the target group should be ITI and Diploma colleges. The team is maintaining a proper database of eligible aspirants, which will help ensure timely mobilization and enable us to commence each batch as planned. | T5: =IF(AND(OR(Dashboard!$B$5="All Managers",A5=Dashboard!$B$5),OR(Dashboard!$E$5="All Centres",B5=Dashboard!$E$5)),1,0) | U5: =IF(T5=1,COUNTIF($T$2:T5,1),"")
A6: Amit Chakraborty | B6: Barasat | C6: GROW Youth-JPM | D6: 2026-07-06 | E6: 6 | F6: 1 | G6: 1 | H6: 5 | I6: 2 | J6: 1 | K6: 12 | L6: 5 | M6: 5 | N6: 9 | O6: 0 | P6: 2 | Q6: During the visit, I identified and highlighted a few operational areas that were being overlooked in day-to-day activities. The discussion focused on establishing a more organized approach/tracker to monitor these activities through simple tracking regular reviews. Most operational processes at the center are functioning well | R6: All is Well | S6: Batch size is the struggle I reviewed the planned batch start date as of now and will keep tracking mobilization pipeline, counselling status and expected joining numbers every week so that I can identify risks at least 1 weeks before the batch start and create an action plan to ensure maintaining expected batch size | T6: =IF(AND(OR(Dashboard!$B$5="All Managers",A6=Dashboard!$B$5),OR(Dashboard!$E$5="All Centres",B6=Dashboard!$E$5)),1,0) | U6: =IF(T6=1,COUNTIF($T$2:T6,1),"")
A7: Bhargav Challa | B7: Warangal | C7: Grow Youth | D7: 2026-07-07 | E7: 5 | F7: 2 | G7: 1 | H7: 6 | I7: 1 | J7: 1 | K7: 6 | L7: 6 | M7: 10 | N7: 9 | O7: 0 | P7: 2 | R7: Connect the centre team with employers and arrange for interviews to make placemnets for batch 14 and remaining students from batch -13 | S7: Have identified and allocated a Tele Caller for next 10 days to do telecalling form the data generated through lokal app and other sources for thestart of Batch-16 at Warangal by 20th July | T7: =IF(AND(OR(Dashboard!$B$5="All Managers",A7=Dashboard!$B$5),OR(Dashboard!$E$5="All Centres",B7=Dashboard!$E$5)),1,0) | U7: =IF(T7=1,COUNTIF($T$2:T7,1),"")
A8: Raghavender Rao | B8: CFRSI-Chandanagar | C8: CFRSI-Innocation | D8: 2026-07-07 | E8: 7 | F8: 0 | G8: 1 | H8: 7 | I8: 0 | J8: 1 | K8: 12 | L8: 7 | M8: 3 | N8: 11 | O8: 0 | P8: 0 | Q8: we have prepared a structured outreach plan. Based on this plan, we are targeting the inception of the Pharma 3rd Batch. Additionally, the team will place greater emphasis on increasing the Digital batch inception count through focused outreach, mobilization, and candidate conversions to achieve the planned enrollment targets. | R8: Based on my network, I have shared potential employer leads, coordinated with institutions to conduct campus drives, and forwarded the employer details to the AH team for further follow-up and execution. | S8: Special focus was given to the Pharma batch. They required a database of Telangana college principals, including contact details of principals from private colleges. I have shared the required database with the team to support their outreach and mobilization efforts. | T8: =IF(AND(OR(Dashboard!$B$5="All Managers",A8=Dashboard!$B$5),OR(Dashboard!$E$5="All Centres",B8=Dashboard!$E$5)),1,0) | U8: =IF(T8=1,COUNTIF($T$2:T8,1),"")
A9: Amit Chakraborty | B9: Dumdum | C9: GROW Youth-CITI | D9: 2026-07-08 | E9: 6 | F9: 1 | G9: 1 | H9: 5 | I9: 2 | J9: 1 | K9: 11 | L9: 6 | M9: 5 | N9: 9 | O9: 0 | P9: 2 | Q9: Few process understanding Gap- Had a discussion with AH and Trainer giving them Clarity on Mock Interview Process and how it needs to be resolved and organized through following MDP guidelines. Requested AH to go through MDP course in Skilify | R9: All is well | S9: All is Well. | T9: =IF(AND(OR(Dashboard!$B$5="All Managers",A9=Dashboard!$B$5),OR(Dashboard!$E$5="All Centres",B9=Dashboard!$E$5)),1,0) | U9: =IF(T9=1,COUNTIF($T$2:T9,1),"")
A10: Mahaboob Basha | B10: Ambattur | C10: SCGBS-GROW-GREEN-EV | D10: 2026-07-10 | E10: 7 | F10: 1 | G10: 0 | H10: 7 | I10: 1 | J10: 0 | K10: 14 | L10: 4 | M10: 4 | N10: 9 | O10: 2 | P10: 0 | Q10: Prepare for audit (precheck) | R10: Employer connect | S10: Support on outreach | T10: =IF(AND(OR(Dashboard!$B$5="All Managers",A10=Dashboard!$B$5),OR(Dashboard!$E$5="All Centres",B10=Dashboard!$E$5)),1,0) | U10: =IF(T10=1,COUNTIF($T$2:T10,1),"")
A11: Amit Chakraborty | B11: Danapur | C11: GROW Youth-Accenture | D11: 2026-07-10 | E11: 4 | F11: 3 | G11: 1 | H11: 4 | I11: 3 | J11: 1 | K11: 9 | L11: 8 | M11: 5 | N11: 8 | O11: 1 | P11: 2 | Q11: My Centre visit this time was to identify process non-compliance and veracity issues. Based on the evidence gathered, the findings indicate a serious breach of data integrity was observed under the AH. The visit provided valuable insights into several underlying operational gaps that were not previously visible. These observations have enabled me to make more informed decisions to strengthen the center's operations, ensure alignment with organizational objectives, and implement corrective measures to minimize process deviations and compliance issues. | R11: With the resignation of the Trainer, there is a risk of delayed placement activities for Batch-80 and a potential impact on placement outcomes. Additionally, as AH also needs to be removed due to veracity issue, need to immediately align AH profiles for the Centre Conduct regular follow-ups with the team on the placement progress of Batch-80 and closely monitor daily placement activities. Align the AH-EC also with the center to facilitate timely placement opportunities a | S11: CA has been taking frequent leaves citing multiple reasons. Despite prior counseling and a formal warning regarding attendance and accountability, the pattern of unplanned leave has continued, impacting Centre operations, mobilization activities, and overall team stability. Action Point- Immediate support will be extended to source suitable CVs for a replacement CA to ensure continuity along. | T11: =IF(AND(OR(Dashboard!$B$5="All Managers",A11=Dashboard!$B$5),OR(Dashboard!$E$5="All Centres",B11=Dashboard!$E$5)),1,0) | U11: =IF(T11=1,COUNTIF($T$2:T11,1),"")
A12: Barna | B12: Daryaganj | C12: CITI Youth | D12: 2026-07-07 | E12: 5 | F12: 2 | G12: 1 | H12: 7 | I12: 0 | J12: 1 | K12: 10 | L12: 7 | M12: 5 | N12: 8 | O12: 0 | P12: 3 | Q12: Explain how to fill and maintain the Alumni Handholding & top 20 format and importance of the process. | R12: Provide Employer's leads initiate the batch placements for the current financial year. | S12: Share an outreach activities format where they can plan the weekly activity and number of leads and footfall generated from the activities. | T12: =IF(AND(OR(Dashboard!$B$5="All Managers",A12=Dashboard!$B$5),OR(Dashboard!$E$5="All Centres",B12=Dashboard!$E$5)),1,0) | U12: =IF(T12=1,COUNTIF($T$2:T12,1),"")
A13: Barna | B13: Shahdara | C13: Accenture (Youth) | D13: 2026-07-08 | E13: 5 | F13: 2 | G13: 1 | H13: 7 | I13: 0 | J13: 1 | K13: 9 | L13: 7 | M13: 6 | N13: 8 | O13: 0 | P13: 3 | Q13: Ensure that the Top 20 Employer List is maintained and regularly updated at the center. Team meetings should be formalized and documented either in the prescribed Team Meeting Format or through email. | R13: Ensuring that L&D mock interview must be maintained. | S13: Once again I explain the counselling check list and Pre ESA part. | T13: =IF(AND(OR(Dashboard!$B$5="All Managers",A13=Dashboard!$B$5),OR(Dashboard!$E$5="All Centres",B13=Dashboard!$E$5)),1,0) | U13: =IF(T13=1,COUNTIF($T$2:T13,1),"")
A14: Amit Chakraborty | B14: Kidwainagar | C14: Grow Youth-Accenture | D14: 2026-07-11 | E14: 3 | F14: 4 | G14: 1 | H14: 5 | I14: 2 | J14: 1 | K14: 10 | L14: 7 | M14: 5 | N14: 8 | O14: 1 | P14: 2 | Q14: As AH had resigned - Sourced few AH CV to immediately close the indent. Completed Day 10 report and removed non eligible candidate, including one underage aspirant where DOB was wrongly updated in Portal. Identified issues in System- 4 system not working and most need repairing of CPU power button | R14: I shall bre in touch with Batch 84 & 85, already spoken and met with some aspirants of the Batch to complete their Placement- Have shared them WFH opportunity at Startek and also, I shall talk to few more Employers to line up candidate. Weekly once I will connect to team on Placement improvement of the Batch till AH joins and support them with lead- I will also connect Rituparna our AH-EC to support them with local /good leads | S14: All is well till now Batches are starting on time | T14: =IF(AND(OR(Dashboard!$B$5="All Managers",A14=Dashboard!$B$5),OR(Dashboard!$E$5="All Centres",B14=Dashboard!$E$5)),1,0) | U14: =IF(T14=1,COUNTIF($T$2:T14,1),"")
A15: Bhargav Challa | B15: Gachibowli | C15: Grow Youth | D15: 2026-07-11 | E15: 4 | F15: 3 | G15: 1 | H15: 3 | I15: 4 | J15: 1 | K15: 4 | L15: 11 | M15: 7 | N15: 6 | O15: 3 | P15: 2 | Q15: Have oriented the team on following the mandatory centre processes of Mock Interview, Weekly Team Meeting, 25th day Aspirant report, maintaining hygeine of the centre. | S15: Guided the team on the importance of planning for mobilisation, focusing on referrals for upcoming batches, and effectively utilizing the AFR, Field Register, and CA Diary. Thsi would help in streamlining the outrech activities and help the batch start | T15: =IF(AND(OR(Dashboard!$B$5="All Managers",A15=Dashboard!$B$5),OR(Dashboard!$E$5="All Centres",B15=Dashboard!$E$5)),1,0) | U15: =IF(T15=1,COUNTIF($T$2:T15,1),"")
A16: Gagandeep Singh Sachar | B16: Vadodara Citi | C16: GROW youth | D16: 2026-07-01 | E16: 5 | F16: 2 | G16: 1 | H16: 5 | I16: 2 | J16: 1 | K16: 15 | L16: 1 | M16: 6 | N16: 9 | O16: 0 | P16: 2 | Q16: Trainer Resigned, Looked for 2-3 resume and done 1 interview | R16: Placement plan disscussed and also 2 employer connect shared | S16: New Tools planning done | T16: =IF(AND(OR(Dashboard!$B$5="All Managers",A16=Dashboard!$B$5),OR(Dashboard!$E$5="All Centres",B16=Dashboard!$E$5)),1,0) | U16: =IF(T16=1,COUNTIF($T$2:T16,1),"")
A17: Gagandeep Singh Sachar | B17: Vadodara HQHCS | C17: HQHCS | D17: 2026-07-02 | E17: 5 | F17: 3 | G17: 0 | H17: 6 | I17: 1 | J17: 1 | K17: 11 | L17: 6 | M17: 5 | N17: 8 | O17: 2 | P17: 1 | Q17: All Process orientation given and aligned with new project and planning | R17: Start seeing the quality of employers | S17: Review Mobilisation plan on weekly basis by deepak | T17: =IF(AND(OR(Dashboard!$B$5="All Managers",A17=Dashboard!$B$5),OR(Dashboard!$E$5="All Centres",B17=Dashboard!$E$5)),1,0) | U17: =IF(T17=1,COUNTIF($T$2:T17,1),"")
A18: Gagandeep Singh Sachar | B18: Vasai | C18: Grow youth | D18: 2026-07-13 | E18: 5 | F18: 2 | G18: 1 | H18: 7 | I18: 0 | J18: 1 | K18: 10 | L18: 5 | M18: 7 | N18: 8 | O18: 1 | P18: 2 | Q18: NA Case - 15 pending for Vasai - discuss with Sushma | R18: Placement to be completed in 15 days. | S18: its going well, New 1-2 mobilisation tools can be added | T18: =IF(AND(OR(Dashboard!$B$5="All Managers",A18=Dashboard!$B$5),OR(Dashboard!$E$5="All Centres",B18=Dashboard!$E$5)),1,0) | U18: =IF(T18=1,COUNTIF($T$2:T18,1),"")
A19: Barna | B19: Sarita Vihar | C19: Youth | D19: 2026-07-11 | E19: 6 | F19: 1 | G19: 1 | H19: 7 | I19: 0 | J19: 1 | K19: 12 | L19: 6 | M19: 4 | N19: 11 | O19: 0 | P19: 0 | Q19: Conducting video calls to clear the NA cases. | R19: Share employer leads with AH | S19: guided on the new outreach activities to be conducted and how to meassure footfalls and leads generated from the activities. | T19: =IF(AND(OR(Dashboard!$B$5="All Managers",A19=Dashboard!$B$5),OR(Dashboard!$E$5="All Centres",B19=Dashboard!$E$5)),1,0) | U19: =IF(T19=1,COUNTIF($T$2:T19,1),"")
A20: Barna | B20: NOIDA Sec 63 | C20: GROW Youth | D20: 2026-07-13 | E20: 3 | F20: 2 | G20: 3 | H20: 6 | I20: 1 | J20: 1 | K20: 6 | L20: 8 | M20: 8 | N20: 0 | O20: 0 | P20: 11 | Q20: Discuss with CA review the outreach efforts. | R20: Clarity given on the collection of Placement evidences. | S20: Reviewing the outreach activities. | T20: =IF(AND(OR(Dashboard!$B$5="All Managers",A20=Dashboard!$B$5),OR(Dashboard!$E$5="All Centres",B20=Dashboard!$E$5)),1,0) | U20: =IF(T20=1,COUNTIF($T$2:T20,1),"")
A21: Amit Chakraborty | B21: Alambagh | C21: GROW Youth-Accenture | D21: 2026-07-13 | E21: 4 | F21: 3 | G21: 1 | H21: 3 | I21: 3 | J21: 2 | K21: 15 | L21: 2 | M21: 5 | N21: 9 | O21: 0 | P21: 2 | Q21: 1 Trainer Resigned had interview 3 Profile and finalized 2 and shared CV with Trainer | R21: Present performance of FY 26-27 is good only need to keep on tracking FY 25-26 and support team with new Employers | S21: All is well. Present batch is delayed starting by 3-4 days and average B2 be around 7 days . Had a discussion with team on Planned batch start date which is delayed it shall start in next 3 days | T21: =IF(AND(OR(Dashboard!$B$5="All Managers",A21=Dashboard!$B$5),OR(Dashboard!$E$5="All Centres",B21=Dashboard!$E$5)),1,0) | U21: =IF(T21=1,COUNTIF($T$2:T21,1),"")
A22: Gagandeep Singh Sachar | B22: Thane | C22: Youth | D22: 2026-07-14 | E22: 5 | F22: 2 | G22: 1 | H22: 4 | I22: 2 | J22: 2 | K22: 10 | L22: 5 | M22: 7 | N22: 8 | O22: 1 | P22: 2 | Q22: AH interview for Belapur Done - Akshay | R22: NA case discussion | S22: No issue | T22: =IF(AND(OR(Dashboard!$B$5="All Managers",A22=Dashboard!$B$5),OR(Dashboard!$E$5="All Centres",B22=Dashboard!$E$5)),1,0) | U22: =IF(T22=1,COUNTIF($T$2:T22,1),"")
A23: Amit Chakraborty | B23: Lucknow-Indiranagar | C23: GROW Youth-CITI | D23: 2026-07-14 | E23: 6 | F23: 1 | G23: 1 | H23: 7 | I23: 0 | J23: 1 | K23: 17 | L23: 0 | M23: 5 | N23: 9 | O23: 0 | P23: 2 | Q23: Guided them on New QAE Pilot on Lucknow Indiranagar, gave them clarity on FCRA challenge they were facing | R23: All is Well- Benchmark Salary is a concern-Guided team on Planning well on Each Aspirants to ensure Placement is aligned | S23: All is well | T23: =IF(AND(OR(Dashboard!$B$5="All Managers",A23=Dashboard!$B$5),OR(Dashboard!$E$5="All Centres",B23=Dashboard!$E$5)),1,0) | U23: =IF(T23=1,COUNTIF($T$2:T23,1),"")
A24: Mahaboob Basha | B24: Velachery-Accenture Additional Grant | C24: GROW-Youth | D24: 2026-07-15 | E24: 7 | F24: 0 | G24: 1 | H24: 5 | I24: 1 | J24: 2 | K24: 15 | L24: 4 | M24: 3 | N24: 9 | O24: 2 | P24: 0 | Q24: Meeting with CA on performance | R24: Employer connect | S24: Data collection and outreach plan | T24: =IF(AND(OR(Dashboard!$B$5="All Managers",A24=Dashboard!$B$5),OR(Dashboard!$E$5="All Centres",B24=Dashboard!$E$5)),1,0) | U24: =IF(T24=1,COUNTIF($T$2:T24,1),"")
A25: Gagandeep Singh Sachar | B25: Swargate | C25: GROW | D25: 2026-07-15 | E25: 6 | F25: 1 | G25: 1 | H25: 7 | I25: 0 | J25: 1 | K25: 16 | L25: 0 | M25: 6 | N25: 10 | O25: 0 | P25: 1 | Q25: NA cases - Rejected due to BBM approval and Discuss with vendor on door repair | R25: Discuss aspirants 1-1 for all un placed | S25: Batch to start on time - We have discussed on the use of multiple tools | T25: =IF(AND(OR(Dashboard!$B$5="All Managers",A25=Dashboard!$B$5),OR(Dashboard!$E$5="All Centres",B25=Dashboard!$E$5)),1,0) | U25: =IF(T25=1,COUNTIF($T$2:T25,1),"")
A26: Sanjay Kumar Tarai | B26: Berhampur | C26: CITI | D26: 2026-07-14 | E26: 4 | F26: 3 | G26: 1 | H26: 5 | I26: 2 | J26: 1 | K26: 10 | L26: 8 | M26: 4 | N26: 8 | O26: 1 | P26: 2 | Q26: Weak process ownership and supervisory control at the centre level, leading to poor compliance, inconsistent training quality, delayed execution, and lack of accountability. New AH- Lack of managerial supervision by the Area Head (AH), still he needs handhold for couple of months till one complete batch cycle end. The centre currently lacks a disciplined Review, Feedback , Follow-up, Closure mechanism. I have clearly discussed with all team members and ensure all follows the agreed action points. Daily checklist review (HK, Trainer, CA). 15-minute morning planning meeting. End-of-day review of pending activities. Weekly classroom observation. Weekly documentation audit. Weekly placement and employer review. Weekly action tracker with target dates and closure status. | R26: As a second-level manager, I can improve placement percentage by institutionalizing a weekly placement management system that reviews the employer pipeline, candidate readiness. I can send weekly atlease one placement opportunity where Berhampur candidates can be placed. | S26: I engage myself in morning to discuss daily outreach planning, tools to be used for the day, areas with my suggestion wherever required to do it in better way and do review in daily evening for 10 min with CA and AH. | T26: =IF(AND(OR(Dashboard!$B$5="All Managers",A26=Dashboard!$B$5),OR(Dashboard!$E$5="All Centres",B26=Dashboard!$E$5)),1,0) | U26: =IF(T26=1,COUNTIF($T$2:T26,1),"")
A27: Bhargav Challa | B27: Bachupally | C27: Grow Youth | D27: 2026-07-15 | E27: 5 | F27: 2 | G27: 1 | H27: 6 | I27: 1 | J27: 1 | K27: 14 | L27: 2 | M27: 6 | N27: 7 | O27: 2 | P27: 2 | Q27: Oriented the centre on the need to follow the key process to be followed- Regularity and punctuality of the students, Transparent reporting of the data and their understanding of the programme | R27: Counseled the Batch-11 students to understand their career aspirations and preferred job roles. Developed a placement plan and interview line up's to ensure all students are placed within the next two weeks, in coordination with Sachin and the batch trainer. | T27: =IF(AND(OR(Dashboard!$B$5="All Managers",A27=Dashboard!$B$5),OR(Dashboard!$E$5="All Centres",B27=Dashboard!$E$5)),1,0) | U27: =IF(T27=1,COUNTIF($T$2:T27,1),"")
A28: Barna | B28: Nehru Nagar Durg | C28: Youth Accenture | D28: 2026-07-15 | E28: 4 | F28: 3 | G28: 1 | H28: 5 | I28: 2 | J28: 1 | K28: 8 | L28: 7 | M28: 7 | N28: 9 | O28: 0 | P28: 2 | Q28: Explained the assets Verification process | R28: Share Placement leads to conduct a campus drive at center. | S28: share a weekly outreach activity format Planned Vs Actuals. In that sheet defined 20+ outreach activities which needs to be carried out on weekly basis. Also Prepared a google form which capture basic information of the jobless candidates. It can be shared along with Whatsapp flyer. | T28: =IF(AND(OR(Dashboard!$B$5="All Managers",A28=Dashboard!$B$5),OR(Dashboard!$E$5="All Centres",B28=Dashboard!$E$5)),1,0) | U28: =IF(T28=1,COUNTIF($T$2:T28,1),"")
A29: Barna | B29: Gurgaon | C29: Youth (CITI) | D29: 2026-07-10 | E29: 7 | F29: 0 | G29: 1 | H29: 6 | I29: 1 | J29: 1 | K29: 10 | L29: 7 | M29: 5 | N29: 9 | O29: 0 | P29: 2 | Q29: NA cases discussed with AH. So that she can cleared it as soon as possible. | R29: Two employer leads shared with AH | S29: Weekly outreach sheet shared with the AH and CA. It will help them to planning the outreach activities | T29: =IF(AND(OR(Dashboard!$B$5="All Managers",A29=Dashboard!$B$5),OR(Dashboard!$E$5="All Centres",B29=Dashboard!$E$5)),1,0) | U29: =IF(T29=1,COUNTIF($T$2:T29,1),"")
A30: Barna | B30: Peeragarhi | C30: Youth CITI | D30: 2026-07-09 | E30: 5 | F30: 2 | G30: 1 | H30: 7 | I30: 0 | J30: 1 | K30: 9 | L30: 7 | M30: 6 | N30: 9 | O30: 0 | P30: 2 | Q30: Explain and aligned AH how placements and skill shift will takes place. | R30: Planning is done for the placements and discuss the dates for the batchwise placement closure reports to be shared. | S30: Explaining the Weekly outreach format and ensuring that it should be implemented as per the plan. | T30: =IF(AND(OR(Dashboard!$B$5="All Managers",A30=Dashboard!$B$5),OR(Dashboard!$E$5="All Centres",B30=Dashboard!$E$5)),1,0) | U30: =IF(T30=1,COUNTIF($T$2:T30,1),"")
A31: Gagandeep Singh Sachar | B31: Chinchwad - Pune | C31: Youth | D31: 2026-07-16 | E31: 6 | F31: 1 | G31: 1 | H31: 6 | I31: 1 | J31: 1 | K31: 10 | L31: 7 | M31: 5 | N31: 10 | O31: 0 | P31: 1 | Q31: Issue for light - Need to give a backup generator and Train will join from 20th July at center | R31: EC more need to be done. | S31: Data collection and Training to CA | T31: =IF(AND(OR(Dashboard!$B$5="All Managers",A31=Dashboard!$B$5),OR(Dashboard!$E$5="All Centres",B31=Dashboard!$E$5)),1,0) | U31: =IF(T31=1,COUNTIF($T$2:T31,1),"")
A32: Amit Chakraborty | B32: Bareilly | C32: GROW Youth- Accenture | D32: 2026-07-15 | E32: 6 | F32: 1 | G32: 1 | H32: 3 | I32: 4 | J32: 1 | K32: 13 | L32: 4 | M32: 5 | N32: 5 | O32: 4 | P32: 2 | Q32: 1)Identified process gap and trained team on Process 2) Qulaity Placement is a concern so guided team to share aspirant wise placement plan 3) Conducted session with Aspirants and cleared them on importance of Skillify courses and Refferal policy 4) AH session and Mock Interview found missing- Will track the same 5) In present batch it was found around 14 candidate are not regular and alligned-Attendance found poor- Removed all unserious candidate and discussed and guided team on Counselling process | R32: 1) Every week discussion and Plan on unplaced candidate shall be done with Bareilly Team 2) Will arrange a Personal counselling on relocation to Delhi/Noida will do | S32: Batch start is not a challenge huge dropout/removal has been a challenge - So I will personally monitor Day 1 report and if needed 1 to 1 interaction with Aspirant in next Batch | T32: =IF(AND(OR(Dashboard!$B$5="All Managers",A32=Dashboard!$B$5),OR(Dashboard!$E$5="All Centres",B32=Dashboard!$E$5)),1,0) | U32: =IF(T32=1,COUNTIF($T$2:T32,1),"")
A33: Barna | B33: Narmada Nagar Bilaspur | C33: Youth Accenture | D33: 2026-07-16 | E33: 7 | F33: 0 | G33: 1 | H33: 5 | I33: 2 | J33: 1 | K33: 9 | L33: 7 | M33: 6 | N33: 9 | O33: 0 | P33: 2 | Q33: Discussed on all the old NA cases | R33: Provided Leads for the placements | S33: Share and discussed the Weekly outreach sheet and ensure that all the mentioned activities must be implemented as per the plan. | T33: =IF(AND(OR(Dashboard!$B$5="All Managers",A33=Dashboard!$B$5),OR(Dashboard!$E$5="All Centres",B33=Dashboard!$E$5)),1,0) | U33: =IF(T33=1,COUNTIF($T$2:T33,1),"")
A34: Amit Chakraborty | B34: Baccha Park | C34: GROW Youth-Accenture | D34: 2026-07-16 | E34: 6 | F34: 0 | G34: 2 | H34: 4 | I34: 3 | J34: 1 | K34: 15 | L34: 2 | M34: 5 | N34: 9 | O34: 0 | P34: 2 | Q34: No major challenge observed in Centre. I conducted a session of Batch 88 on explaining Local and Out location opportunities in Meerut and around and benefit of joining Quality Organization | R34: Local placement opportunities continue to be a challenge in the region. To address this, I have already shared available job opportunities from Digitide and Tech Mahindra with the centre team. I will conduct an awareness and counselling session with the aspirants to help them understand the benefits of relocation, including better career prospects, higher employability, and long-term career growth. This will encourage greater willingness among aspirants to explore opportunities outside their local area | S34: All is well | T34: =IF(AND(OR(Dashboard!$B$5="All Managers",A34=Dashboard!$B$5),OR(Dashboard!$E$5="All Centres",B34=Dashboard!$E$5)),1,0) | U34: =IF(T34=1,COUNTIF($T$2:T34,1),"")
A35: Barna | B35: Lakhe Nagar Raipur | C35: Youth Accenture | D35: 2026-07-14 | E35: 5 | F35: 2 | G35: 1 | H35: 6 | I35: 1 | J35: 1 | K35: 9 | L35: 7 | M35: 6 | N35: 10 | O35: 0 | P35: 1 | Q35: Ensuring CA should collect the 10th Class marksheet for DOB. Team is collecting only last higher education proofs. | R35: Ensuring daily 8-10 interviews must be scheduled for both the programs. Also Shared employer connect lead | S35: The team is facing challenges in conducting online outreach. We discussed and planned the outreach strategy, and explained how they should carry forward the outreach activities to ensure timely batch starts. | T35: =IF(AND(OR(Dashboard!$B$5="All Managers",A35=Dashboard!$B$5),OR(Dashboard!$E$5="All Centres",B35=Dashboard!$E$5)),1,0) | U35: =IF(T35=1,COUNTIF($T$2:T35,1),"")
A36: Mahaboob Basha | B36: Coimbatore | C36: GROW-Youth-CITI | D36: 2026-07-17 | E36: 3 | F36: 4 | G36: 1 | H36: 7 | I36: 0 | J36: 1 | K36: 15 | L36: 1 | M36: 6 | N36: 10 | O36: 0 | P36: 1 | Q36: Met 2 employer at their place with AH, Found some gap in registration form, Check list and corrected | R36: Connect with the employer and set the aspirant mindset on day 1 | S36: Connect with community | T36: =IF(AND(OR(Dashboard!$B$5="All Managers",A36=Dashboard!$B$5),OR(Dashboard!$E$5="All Centres",B36=Dashboard!$E$5)),1,0) | U36: =IF(T36=1,COUNTIF($T$2:T36,1),"")
A37: Gagandeep Singh Sachar | B37: Pune Green | C37: Grow Green | D37: 2026-07-17 | E37: 4 | F37: 1 | G37: 3 | H37: 5 | I37: 2 | J37: 1 | K37: 7 | L37: 4 | M37: 11 | N37: 6 | O37: 4 | P37: 1 | Q37: Infra Readiness mail and discussion done with abhishek, Discuss with hostel vendor to proper quality service | R37: EC - Need to improve and will share 2 EC lead generated today | S37: We have discuss different mobilization strategies and we agreed to focus entirely on ITI, Diploma and polytechnical | T37: =IF(AND(OR(Dashboard!$B$5="All Managers",A37=Dashboard!$B$5),OR(Dashboard!$E$5="All Centres",B37=Dashboard!$E$5)),1,0) | U37: =IF(T37=1,COUNTIF($T$2:T37,1),"")
A38: Gagandeep Singh Sachar | B38: Bund Garden Pune | C38: GROW | D38: 2026-07-18 | E38: 7 | F38: 0 | G38: 1 | H38: 4 | I38: 2 | J38: 2 | K38: 14 | L38: 2 | M38: 6 | N38: 9 | O38: 1 | P38: 1 | Q38: Training to both new CA and make them understand about outreach and mobilization, Discussion on process | R38: Need to support in EC and also discuss 1-1 aspirants | S38: Training Give to CA and importance of Right candidate | T38: =IF(AND(OR(Dashboard!$B$5="All Managers",A38=Dashboard!$B$5),OR(Dashboard!$E$5="All Centres",B38=Dashboard!$E$5)),1,0) | U38: =IF(T38=1,COUNTIF($T$2:T38,1),"")
A39: Gagandeep Singh Sachar | B39: Jogeshwari | C39: GROW | D39: 2026-07-20 | E39: 5 | F39: 2 | G39: 1 | H39: 7 | I39: 0 | J39: 1 | K39: 11 | L39: 5 | M39: 6 | N39: 7 | O39: 3 | P39: 1 | Q39: NA Cases - Discuss with Sarita and 7 (5+2) got clear | R39: Unplaced - Discussion done - 1-1 | S39: Data purchase with Job Hai to be plan and Nikita | T39: =IF(AND(OR(Dashboard!$B$5="All Managers",A39=Dashboard!$B$5),OR(Dashboard!$E$5="All Centres",B39=Dashboard!$E$5)),1,0) | U39: =IF(T39=1,COUNTIF($T$2:T39,1),"")
... A43: Amit Chakraborty | B43: Dankuni | C43: Grow Youth-CITI | D43: 2026-07-21 | E43: 6 | F43: 0 | G43: 2 | H43: 6 | I43: 1 | J43: 1 | K43: 16 | L43: 1 | M43: 5 | N43: 9 | O43: 0 | P43: 2 | Q43: 7 NA was cleared and discussed on Plan to clear NA by next 1 week | R43: NA clearance is one most priority for Dankuni centre | S43: All is well and Batches are starting on time | T43: =IF(AND(OR(Dashboard!$B$5="All Managers",A43=Dashboard!$B$5),OR(Dashboard!$E$5="All Centres",B43=Dashboard!$E$5)),1,0) | U43: =IF(T43=1,COUNTIF($T$2:T43,1),"")
A44: Bhargav Challa | B44: Nalgonda | C44: Grow Youth | D44: 2026-07-20 | E44: 7 | F44: 0 | G44: 1 | H44: 5 | I44: 2 | J44: 1 | K44: 16 | L44: 1 | M44: 5 | N44: 7 | O44: 2 | P44: 2 | T44: =IF(AND(OR(Dashboard!$B$5="All Managers",A44=Dashboard!$B$5),OR(Dashboard!$E$5="All Centres",B44=Dashboard!$E$5)),1,0) | U44: =IF(T44=1,COUNTIF($T$2:T44,1),"")
A45: Bhargav Challa | B45: Secunderabad | C45: Youth | D45: 2026-07-21 | E45: 5 | F45: 2 | G45: 1 | H45: 7 | I45: 0 | J45: 1 | K45: 15 | L45: 3 | M45: 4 | N45: 8 | O45: 1 | P45: 2 | R45: *Have worked on the placement plan and mapping of aspirants for interviews from the April batch *Spoke to the survelliance company to clear NA cases given the issues in the offer letter | S45: *Supporting the Centre team in hiring of the CA and sourcing of profiles is in process | T45: =IF(AND(OR(Dashboard!$B$5="All Managers",A45=Dashboard!$B$5),OR(Dashboard!$E$5="All Centres",B45=Dashboard!$E$5)),1,0) | U45: =IF(T45=1,COUNTIF($T$2:T45,1),"")
A46: Raghavender Rao | B46: Tech jobs-Miyapur | C46: Tech jobs | D46: 2026-07-22 | E46: 7 | F46: 0 | G46: 1 | H46: 6 | I46: 0 | J46: 2 | K46: 18 | L46: 1 | M46: 3 | N46: 8 | O46: 1 | P46: 2 | Q46: More focus on employer connect instead of cold calling | R46: More focus on startups | S46: Here mobilization is not a challenge, major challenge is righ candidate selection& Pre assesment score | T46: =IF(AND(OR(Dashboard!$B$5="All Managers",A46=Dashboard!$B$5),OR(Dashboard!$E$5="All Centres",B46=Dashboard!$E$5)),1,0) | U46: =IF(T46=1,COUNTIF($T$2:T46,1),"")
A47: Barna | B47: Shanti Nagar Raipur CITI | C47: Youth | D47: 2026-07-17 | E47: 6 | F47: 1 | G47: 1 | H47: 6 | I47: 1 | J47: 1 | K47: 15 | L47: 3 | M47: 4 | N47: 9 | O47: 0 | P47: 2 | Q47: Team meeting register not found at center guided team to request for the same | R47: Leads provided for Kalyan Jwellers, zudio and Quess corp (Grahak Mitra) | S47: Shared a list of outreach activity to get maximum footfalls at center. | T47: =IF(AND(OR(Dashboard!$B$5="All Managers",A47=Dashboard!$B$5),OR(Dashboard!$E$5="All Centres",B47=Dashboard!$E$5)),1,0) | U47: =IF(T47=1,COUNTIF($T$2:T47,1),"")
A48: Barna | B48: Nanda Nagar center | C48: Youth | D48: 2026-07-20 | E48: 7 | F48: 0 | G48: 1 | H48: 6 | I48: 1 | J48: 1 | K48: 14 | L48: 2 | M48: 6 | N48: 9 | O48: 0 | P48: 2 | Q48: discussion done on NA cases for all the center | R48: Discussion done on categorization of employers and Placements on women center. | S48: I discussed with Gokul regarding batch start plan for GDY and Indore Tech (College Seminars) | T48: =IF(AND(OR(Dashboard!$B$5="All Managers",A48=Dashboard!$B$5),OR(Dashboard!$E$5="All Centres",B48=Dashboard!$E$5)),1,0) | U48: =IF(T48=1,COUNTIF($T$2:T48,1),"")
A49: Bhargav Challa | B49: Uppal | C49: Grow Youth | D49: 2026-07-23 | E49: 6 | F49: 1 | G49: 1 | H49: 4 | I49: 3 | J49: 1 | K49: 15 | L49: 2 | M49: 5 | N49: 9 | O49: 0 | P49: 2 | R49: Connected with all unplaced students of Batch-92, collected their interest to go for the job with a plan to line up for the placements | S49: Made an Outreach plan with the support of AH and CA to diversify the channels of mobilisation and pace up the speed of mobilisation | T49: =IF(AND(OR(Dashboard!$B$5="All Managers",A49=Dashboard!$B$5),OR(Dashboard!$E$5="All Centres",B49=Dashboard!$E$5)),1,0) | U49: =IF(T49=1,COUNTIF($T$2:T49,1),"")
A50: S Jakir | B50: Nelamangala | C50: GROW Green Jobs ( Solar ) | D50: 2026-07-23 | E50: 7 | F50: 1 | G50: 0 | H50: 7 | I50: 1 | J50: 0 | K50: 17 | L50: 2 | M50: 3 | N50: 10 | O50: 1 | P50: 0 | Q50: Visted the hostel and discussed with Hostel management regarding few observations . Mainly about the cleanliness and they committed that they will rectify . 2 ) Also discussed placement plan with AH and shared interview lineup inputs . | R50: Job drives need to organize by categorizing the unplaced aspirants . Discussed with AH and guided . I will extend my support . | S50: Team is doing good in mobilization and need to ensure the regular efforts as per the plan . | T50: =IF(AND(OR(Dashboard!$B$5="All Managers",A50=Dashboard!$B$5),OR(Dashboard!$E$5="All Centres",B50=Dashboard!$E$5)),1,0) | U50: =IF(T50=1,COUNTIF($T$2:T50,1),"")
A51: S Jakir | B51: Electronic City | C51: GROW Green Jobs ( EV ) | D51: 2026-07-22 | E51: 7 | F51: 1 | G51: 0 | H51: 8 | I51: 0 | J51: 0 | K51: 16 | L51: 3 | M51: 3 | N51: 11 | O51: 0 | P51: 0 | Q51: Had a discussion with CA Mr Naveen regarding his willingness to resign and guided . Also discussed a hring plan with AH regarding CA hiring ( Additional ) & replacemnet hiring of Naveen incase he decide to resign . | R51: Arranging new employer leads , Close monitoring and regular followup calls with AH . | S51: CA Hiring and completing the induction training soon after the CA joining . Idenfidied few profiles and will complete their interview in next 3 days . | T51: =IF(AND(OR(Dashboard!$B$5="All Managers",A51=Dashboard!$B$5),OR(Dashboard!$E$5="All Centres",B51=Dashboard!$E$5)),1,0) | U51: =IF(T51=1,COUNTIF($T$2:T51,1),"")
A52: S Jakir | B52: Bommanahalli | C52: GROW Youth | D52: 2026-07-22 | E52: 4 | F52: 3 | G52: 1 | H52: 3 | I52: 4 | J52: 1 | K52: 17 | L52: 1 | M52: 4 | N52: 9 | O52: 0 | P52: 2 | Q52: EP Guidlines reinforced & NA cases status discussed . | R52: Regular followup's with AH | S52: No issues in mobilization | T52: =IF(AND(OR(Dashboard!$B$5="All Managers",A52=Dashboard!$B$5),OR(Dashboard!$E$5="All Centres",B52=Dashboard!$E$5)),1,0) | U52: =IF(T52=1,COUNTIF($T$2:T52,1),"")
A53: S Jakir | B53: Jalahalli | C53: GROW Youth | D53: 2026-07-20 | E53: 7 | F53: 0 | G53: 1 | H53: 4 | I53: 3 | J53: 1 | K53: 16 | L53: 2 | M53: 4 | N53: 9 | O53: 0 | P53: 2 | Q53: Discussed with EP Guidlines , AFR filling and NA Cases .Process reinforced once gain . Also conducted Bangalore HK staff refresher training cum meeting conducted in the 2nd half . | R53: Sharing new employer leads especially noth Bangalore region . | S53: Mobilization part team is good | T53: =IF(AND(OR(Dashboard!$B$5="All Managers",A53=Dashboard!$B$5),OR(Dashboard!$E$5="All Centres",B53=Dashboard!$E$5)),1,0) | U53: =IF(T53=1,COUNTIF($T$2:T53,1),"")
A54: S Jakir | B54: Hebbal | C54: GROW Plus | D54: 2026-07-17 | E54: 5 | F54: 2 | G54: 1 | H54: 5 | I54: 2 | J54: 1 | K54: 16 | L54: 1 | M54: 5 | N54: 9 | O54: 0 | P54: 2 | Q54: Key processes reinfoced to team ( Trainer newly joined ) . Conducted a training session on employer connect topic . | R54: New employer leads needs to share and exclusive job drives need to organize . | S54: I will guide CA and Area mapping will revise for better outreach . CA reinforcement training is organizing on 8th August . | T54: =IF(AND(OR(Dashboard!$B$5="All Managers",A54=Dashboard!$B$5),OR(Dashboard!$E$5="All Centres",B54=Dashboard!$E$5)),1,0) | U54: =IF(T54=1,COUNTIF($T$2:T54,1),"")
A55: S Jakir | B55: Uttarahalli | C55: GROW Youth | D55: 2026-07-16 | E55: 6 | F55: 1 | G55: 1 | H55: 4 | I55: 3 | J55: 1 | K55: 16 | L55: 2 | M55: 4 | N55: 10 | O55: 0 | P55: 1 | Q55: Neelu ( Sr AH ) submitted a resignation is Darwin due to better opportunity . I had a detailed discussion with employee , coordinated with Gagan sir and Kalyani mam . Arranged a discussion with Kalyani mam also . Post discussion he asked 1 day time to finalize his decession . | R55: Regular placement discussion needed . | S55: New CA induction training need to complete . I will conduct on 8th August . | T55: =IF(AND(OR(Dashboard!$B$5="All Managers",A55=Dashboard!$B$5),OR(Dashboard!$E$5="All Centres",B55=Dashboard!$E$5)),1,0) | U55: =IF(T55=1,COUNTIF($T$2:T55,1),"")
A56: S Jakir | B56: Hubli | C56: GROW Youth | D56: 2026-07-08 | E56: 6 | F56: 1 | G56: 1 | H56: 7 | I56: 0 | J56: 1 | K56: 16 | L56: 2 | M56: 4 | N56: 11 | O56: 0 | P56: 0 | Q56: Key process reinforced to team & CCTV issue resolved | R56: Need to generate new employer leads and share | S56: Referrals need to improve . Need monitor closely the referral generation activities . | T56: =IF(AND(OR(Dashboard!$B$5="All Managers",A56=Dashboard!$B$5),OR(Dashboard!$E$5="All Centres",B56=Dashboard!$E$5)),1,0) | U56: =IF(T56=1,COUNTIF($T$2:T56,1),"")
A57: S Jakir | B57: Hoskote | C57: HHQCS | D57: 2026-07-15 | E57: 6 | F57: 2 | G57: 0 | H57: 6 | I57: 2 | J57: 0 | K57: 12 | L57: 5 | M57: 5 | N57: 8 | O57: 2 | P57: 1 | Q57: Coducted one to one discussion with all new batch aspirants , identified documentation and counselling gaps . Shared detailed feedback with AH and reinforced the process . | R57: New employers need to identify to improve further placement quality . | S57: CA Offer letter will release by monday ( Discussed with HR Team ) and will conduct CA indcution training soon after that . | T57: =IF(AND(OR(Dashboard!$B$5="All Managers",A57=Dashboard!$B$5),OR(Dashboard!$E$5="All Centres",B57=Dashboard!$E$5)),1,0) | U57: =IF(T57=1,COUNTIF($T$2:T57,1),"")
A58: S Jakir | B58: Thanisandra | C58: GROW Youth | D58: 2026-07-14 | E58: 5 | F58: 2 | G58: 1 | H58: 6 | I58: 1 | J58: 1 | K58: 14 | L58: 4 | M58: 4 | N58: 10 | O58: 0 | P58: 1 | Q58: Conducted process reinforcement discussion with team and clarified their doubts ( Here AH promoted from Trainer role & Smith - New trainer joined recently ) . | R58: Providing employer leads & regular discusion with AH regarding placements | S58: Area mapping need to reinforce and Mobilization budget utilization need to ensure . | T58: =IF(AND(OR(Dashboard!$B$5="All Managers",A58=Dashboard!$B$5),OR(Dashboard!$E$5="All Centres",B58=Dashboard!$E$5)),1,0) | U58: =IF(T58=1,COUNTIF($T$2:T58,1),"")
A59: S Jakir | B59: K R Puram | C59: GROW Youth | D59: 2026-07-07 | E59: 6 | F59: 1 | G59: 1 | H59: 4 | I59: 2 | J59: 2 | K59: 14 | L59: 3 | M59: 5 | N59: 10 | O59: 0 | P59: 1 | Q59: 1 ) Discussed with digital trainer profile and conducted a demo session ( replacement for Digital trainer Mrs Chethana - Planned to go on Maternity leave ) . 2 ) Discussed with newly joined trainer Ms Roopa , understood how she is handling the batch and feedback shared . | R59: I will make sure to revise their top 20 employer list and share new potential employers | S59: i will discuss CA and AH , help him them to revise the are mapping to increase KR Puram surroungs footfalls . | T59: =IF(AND(OR(Dashboard!$B$5="All Managers",A59=Dashboard!$B$5),OR(Dashboard!$E$5="All Centres",B59=Dashboard!$E$5)),1,0) | U59: =IF(T59=1,COUNTIF($T$2:T59,1),"")
A60: S Jakir | B60: Marathahalli | C60: GROW Youth | D60: 2026-07-06 | E60: 5 | F60: 2 | G60: 1 | H60: 5 | I60: 2 | J60: 1 | K60: 15 | L60: 6 | M60: 1 | N60: 10 | O60: 0 | P60: 1 | Q60: Soft skill trainer hiring is completed , Key process reinforced , NA Cases & Unplaced aspirants followup is done and status updated . | R60: Need to generate new employer leads and ensure regular status check with AH | S60: Quality of the aspirants need to improve . Feedback shared with CA & AH . | T60: =IF(AND(OR(Dashboard!$B$5="All Managers",A60=Dashboard!$B$5),OR(Dashboard!$E$5="All Centres",B60=Dashboard!$E$5)),1,0) | U60: =IF(T60=1,COUNTIF($T$2:T60,1),"")
A61: S Jakir | B61: Yelahanka | C61: GROW Youth | D61: 2026-07-11 | E61: 6 | F61: 1 | G61: 1 | H61: 5 | I61: 2 | J61: 1 | K61: 15 | L61: 3 | M61: 4 | N61: 10 | O61: 0 | P61: 1 | Q61: All key process reinfoced ( AH promoted from Trainer role ) , Conducted training session on employer connect . | R61: Employer leads need to share and do regular followup's with AH | S61: Doing good in mobilization | T61: =IF(AND(OR(Dashboard!$B$5="All Managers",A61=Dashboard!$B$5),OR(Dashboard!$E$5="All Centres",B61=Dashboard!$E$5)),1,0) | U61: =IF(T61=1,COUNTIF($T$2:T61,1),"")
... A67: Phani | B67: Kochi CITI | C67: Grow Youth | D67: 2026-07-10 | E67: 5 | F67: 0 | G67: 3 | H67: 4 | I67: 3 | J67: 1 | K67: 12 | L67: 3 | M67: 7 | N67: 8 | O67: 1 | P67: 2 | Q67: I have arranged CA for this center, and went door to door outreach with her and build her capacity in updating AFR | R67: I will go to employer connect along with AH in August | S67: I have arranged CA for this center, and went door to door outreach with her and build her capacity in updating AFR, Spoke to admin and arranged paper ad | T67: =IF(AND(OR(Dashboard!$B$5="All Managers",A67=Dashboard!$B$5),OR(Dashboard!$E$5="All Centres",B67=Dashboard!$E$5)),1,0) | U67: =IF(T67=1,COUNTIF($T$2:T67,1),"")
A68: Phani | B68: Kochi Women | C68: Grow Women | D68: 2026-07-10 | E68: 7 | F68: 0 | G68: 1 | H68: 7 | I68: 0 | J68: 1 | K68: 13 | L68: 1 | M68: 8 | N68: 9 | O68: 0 | P68: 2 | R68: Made AH to update 12 placements | T68: =IF(AND(OR(Dashboard!$B$5="All Managers",A68=Dashboard!$B$5),OR(Dashboard!$E$5="All Centres",B68=Dashboard!$E$5)),1,0) | U68: =IF(T68=1,COUNTIF($T$2:T68,1),"")
A69: Phani | B69: CFRSI Chennai | C69: CFRSI Tech | D69: 2026-07-14 | E69: 5 | F69: 0 | G69: 3 | H69: 7 | I69: 0 | J69: 1 | K69: 12 | L69: 3 | M69: 7 | N69: 8 | O69: 1 | P69: 2 | Q69: Informed to arrange shoe rack | R69: I will go to employer connect with AH in August | T69: =IF(AND(OR(Dashboard!$B$5="All Managers",A69=Dashboard!$B$5),OR(Dashboard!$E$5="All Centres",B69=Dashboard!$E$5)),1,0) | U69: =IF(T69=1,COUNTIF($T$2:T69,1),"")
A70: Phani | B70: Grow Green Ambattur | C70: Grow Green EV | D70: 2026-07-08 | E70: 7 | F70: 1 | G70: 0 | H70: 7 | I70: 1 | J70: 0 | K70: 13 | L70: 4 | M70: 5 | N70: 9 | O70: 1 | P70: 1 | Q70: I have arranged everything and made center ready for partner visit | R70: Clear N/A cases | S70: Provide Hostel admissions | T70: =IF(AND(OR(Dashboard!$B$5="All Managers",A70=Dashboard!$B$5),OR(Dashboard!$E$5="All Centres",B70=Dashboard!$E$5)),1,0) | U70: =IF(T70=1,COUNTIF($T$2:T70,1),"")
A71: Phani | B71: Guindy Solar | C71: Grow Green - Solar | D71: 2026-07-07 | E71: 8 | F71: 0 | G71: 0 | H71: 8 | I71: 0 | J71: 0 | K71: 14 | L71: 4 | M71: 4 | N71: 11 | O71: 0 | P71: 0 | Q71: Arranged center for partner visit | R71: Clear N/A Cases | S71: Extra budget | T71: =IF(AND(OR(Dashboard!$B$5="All Managers",A71=Dashboard!$B$5),OR(Dashboard!$E$5="All Centres",B71=Dashboard!$E$5)),1,0) | U71: =IF(T71=1,COUNTIF($T$2:T71,1),"")
A72: Phani | B72: Gajuwaka | C72: Grow Youth | D72: 2026-07-16 | E72: 5 | F72: 0 | G72: 3 | H72: 5 | I72: 2 | J72: 1 | K72: 8 | L72: 2 | M72: 12 | N72: 8 | O72: 0 | P72: 3 | Q72: Water dispenser purchase is stuck i spoke to admin and finance and on the same day purchased and arranged at center | S72: I have provided school team support for outreach | T72: =IF(AND(OR(Dashboard!$B$5="All Managers",A72=Dashboard!$B$5),OR(Dashboard!$E$5="All Centres",B72=Dashboard!$E$5)),1,0) | U72: =IF(T72=1,COUNTIF($T$2:T72,1),"")
A73: Phani | B73: Akkayapalem | C73: Grow Youth | D73: 2026-07-20 | E73: 7 | F73: 0 | G73: 1 | H73: 7 | I73: 0 | J73: 1 | K73: 17 | L73: 0 | M73: 5 | N73: 9 | O73: 0 | P73: 2 | Q73: Explained IOP to new trainer, arranged trainer material | R73: Given Noida city employer leads | S73: On track | T73: =IF(AND(OR(Dashboard!$B$5="All Managers",A73=Dashboard!$B$5),OR(Dashboard!$E$5="All Centres",B73=Dashboard!$E$5)),1,0) | U73: =IF(T73=1,COUNTIF($T$2:T73,1),"")
A74: Phani | B74: Anakapalli | C74: Grow Youth | D74: 2026-07-22 | E74: 7 | F74: 0 | G74: 1 | H74: 7 | I74: 0 | J74: 1 | K74: 17 | L74: 1 | M74: 4 | N74: 10 | O74: 0 | P74: 1 | R74: On track | S74: On track | T74: =IF(AND(OR(Dashboard!$B$5="All Managers",A74=Dashboard!$B$5),OR(Dashboard!$E$5="All Centres",B74=Dashboard!$E$5)),1,0) | U74: =IF(T74=1,COUNTIF($T$2:T74,1),"")
A75: Phani | B75: Srikakulam | C75: Grow Youth | D75: 2026-07-02 | E75: 7 | F75: 0 | G75: 1 | H75: 4 | I75: 3 | J75: 1 | K75: 17 | L75: 0 | M75: 5 | N75: 9 | O75: 0 | P75: 2 | Q75: Monitors are not working informed AH to take quotation for new monitors | R75: Clearing NA cases | S75: Providing support of school teams | T75: =IF(AND(OR(Dashboard!$B$5="All Managers",A75=Dashboard!$B$5),OR(Dashboard!$E$5="All Centres",B75=Dashboard!$E$5)),1,0) | U75: =IF(T75=1,COUNTIF($T$2:T75,1),"")

Sheet Data
A1: Manager | B1: Centre | C1: Program | D1: Date | E1: Section | F1: Item | G1: Status
A2: Phani | B2: Vijayanagaram | C2: Grow Youth | D2: 2026-07-02 | E2: Data Check | F2: Reach the centre on time (unannounced) — confirm the centre opened on time. | G2: All is Well
A3: Phani | B3: Vijayanagaram | C3: Grow Youth | D3: 2026-07-02 | E3: Data Check | F3: Check the staff attendance register, the Google Sheet, and geo-tagged photos for aspirants. | G3: All is Well
A4: Phani | B4: Vijayanagaram | C4: Grow Youth | D4: 2026-07-02 | E4: Data Check | F4: Check Counselling and Screening Forms of recently started batches. | G4: All is Well
A5: Phani | B5: Vijayanagaram | C5: Grow Youth | D5: 2026-07-02 | E5: Data Check | F5: Check Aspirant Registration Forms and related documents. | G5: All is Well
A6: Phani | B6: Vijayanagaram | C6: Grow Youth | D6: 2026-07-02 | E6: Data Check | F6: On the GROW portal, confirm all student profile details and batch updates are currect. | G6: All is Well
A7: Phani | B7: Vijayanagaram | C7: Grow Youth | D7: 2026-07-02 | E7: Data Check | F7: Verify placement data — randomly call 3–4 alumni placed in the last 3 months to confirm veracity (random selection is essential). | G7: All is Well
A8: Phani | B8: Vijayanagaram | C8: Grow Youth | D8: 2026-07-02 | E8: Data Check | F8: Verify retention — check the Alumni Hand-holding Format is being updated as designed. | G8: All is Well
A9: Phani | B9: Vijayanagaram | C9: Grow Youth | D9: 2026-07-02 | E9: Data Check | F9: Check aspirant Hostel Forms are properly filled or not. | G9: Not Applicable
A10: Phani | B10: Vijayanagaram | C10: Grow Youth | D10: 2026-07-02 | E10: Infra Check | F10: Check all CCTV cameras; if any are not working, ask the AH to troubleshoot or call the vendor. | G10: All is Well
A11: Phani | B11: Vijayanagaram | C11: Grow Youth | D11: 2026-07-02 | E11: Infra Check | F11: Check for any scrap material and get it cleared, with support of Admin | G11: Need Improvement
A12: Phani | B12: Vijayanagaram | C12: Grow Youth | D12: 2026-07-02 | E12: Infra Check | F12: Check for any pending infra repairs. | G12: Need Improvement
... A3627: Phani | B3627: Srikakulam | C3627: Grow Youth | D3627: 2026-07-02 | E3627: Aspirant Interaction | F3627: Ask a few relevant screening questions to support the 10th-day report and remove non-serious candidates, explaining to them the reasons. | G3627: All is Well

Sheet ItemStats
A1: Section | B1: Item | C1: NeedImprovement | D1: AllIsWell | E1: Applicable | F1: PctNeedImprovement | G1: TieBreak
A2: Data Check | B2: Reach the centre on time (unannounced) — confirm the centre opened on time. | C2: =COUNTIFS(Data!$A$2:$A$3627,Dashboard!$B$7,Data!$B$2:$B$3627,Dashboard!$C$7,Data!$E$2:$E$3627,$A2,Data!$F$2:$F$3627,$B2,Data!$G$2:$G$3627,"Need Improvement") | D2: =COUNTIFS(Data!$A$2:$A$3627,Dashboard!$B$7,Data!$B$2:$B$3627,Dashboard!$C$7,Data!$E$2:$E$3627,$A2,Data!$F$2:$F$3627,$B2,Data!$G$2:$G$3627,"All is Well") | E2: =C2+D2 | F2: =IFERROR(C2/E2,0) | G2: =C2+(ROW()/100000)
A3: Data Check | B3: Check the staff attendance register, the Google Sheet, and geo-tagged photos for aspirants. | C3: =COUNTIFS(Data!$A$2:$A$3627,Dashboard!$B$7,Data!$B$2:$B$3627,Dashboard!$C$7,Data!$E$2:$E$3627,$A3,Data!$F$2:$F$3627,$B3,Data!$G$2:$G$3627,"Need Improvement") | D3: =COUNTIFS(Data!$A$2:$A$3627,Dashboard!$B$7,Data!$B$2:$B$3627,Dashboard!$C$7,Data!$E$2:$E$3627,$A3,Data!$F$2:$F$3627,$B3,Data!$G$2:$G$3627,"All is Well") | E3: =C3+D3 | F3: =IFERROR(C3/E3,0) | G3: =C3+(ROW()/100000)
A4: Data Check | B4: Check Counselling and Screening Forms of recently started batches. | C4: =COUNTIFS(Data!$A$2:$A$3627,Dashboard!$B$7,Data!$B$2:$B$3627,Dashboard!$C$7,Data!$E$2:$E$3627,$A4,Data!$F$2:$F$3627,$B4,Data!$G$2:$G$3627,"Need Improvement") | D4: =COUNTIFS(Data!$A$2:$A$3627,Dashboard!$B$7,Data!$B$2:$B$3627,Dashboard!$C$7,Data!$E$2:$E$3627,$A4,Data!$F$2:$F$3627,$B4,Data!$G$2:$G$3627,"All is Well") | E4: =C4+D4 | F4: =IFERROR(C4/E4,0) | G4: =C4+(ROW()/100000)
A5: Data Check | B5: Check Aspirant Registration Forms and related documents. | C5: =COUNTIFS(Data!$A$2:$A$3627,Dashboard!$B$7,Data!$B$2:$B$3627,Dashboard!$C$7,Data!$E$2:$E$3627,$A5,Data!$F$2:$F$3627,$B5,Data!$G$2:$G$3627,"Need Improvement") | D5: =COUNTIFS(Data!$A$2:$A$3627,Dashboard!$B$7,Data!$B$2:$B$3627,Dashboard!$C$7,Data!$E$2:$E$3627,$A5,Data!$F$2:$F$3627,$B5,Data!$G$2:$G$3627,"All is Well") | E5: =C5+D5 | F5: =IFERROR(C5/E5,0) | G5: =C5+(ROW()/100000)
A6: Data Check | B6: On the GROW portal, confirm all student profile details and batch updates are currect. | C6: =COUNTIFS(Data!$A$2:$A$3627,Dashboard!$B$7,Data!$B$2:$B$3627,Dashboard!$C$7,Data!$E$2:$E$3627,$A6,Data!$F$2:$F$3627,$B6,Data!$G$2:$G$3627,"Need Improvement") | D6: =COUNTIFS(Data!$A$2:$A$3627,Dashboard!$B$7,Data!$B$2:$B$3627,Dashboard!$C$7,Data!$E$2:$E$3627,$A6,Data!$F$2:$F$3627,$B6,Data!$G$2:$G$3627,"All is Well") | E6: =C6+D6 | F6: =IFERROR(C6/E6,0) | G6: =C6+(ROW()/100000)
A7: Data Check | B7: Verify placement data — randomly call 3–4 alumni placed in the last 3 months to confirm veracity (random selection is essential). | C7: =COUNTIFS(Data!$A$2:$A$3627,Dashboard!$B$7,Data!$B$2:$B$3627,Dashboard!$C$7,Data!$E$2:$E$3627,$A7,Data!$F$2:$F$3627,$B7,Data!$G$2:$G$3627,"Need Improvement") | D7: =COUNTIFS(Data!$A$2:$A$3627,Dashboard!$B$7,Data!$B$2:$B$3627,Dashboard!$C$7,Data!$E$2:$E$3627,$A7,Data!$F$2:$F$3627,$B7,Data!$G$2:$G$3627,"All is Well") | E7: =C7+D7 | F7: =IFERROR(C7/E7,0) | G7: =C7+(ROW()/100000)
A8: Data Check | B8: Verify retention — check the Alumni Hand-holding Format is being updated as designed. | C8: =COUNTIFS(Data!$A$2:$A$3627,Dashboard!$B$7,Data!$B$2:$B$3627,Dashboard!$C$7,Data!$E$2:$E$3627,$A8,Data!$F$2:$F$3627,$B8,Data!$G$2:$G$3627,"Need Improvement") | D8: =COUNTIFS(Data!$A$2:$A$3627,Dashboard!$B$7,Data!$B$2:$B$3627,Dashboard!$C$7,Data!$E$2:$E$3627,$A8,Data!$F$2:$F$3627,$B8,Data!$G$2:$G$3627,"All is Well") | E8: =C8+D8 | F8: =IFERROR(C8/E8,0) | G8: =C8+(ROW()/100000)
A9: Data Check | B9: Check aspirant Hostel Forms are properly filled or not. | C9: =COUNTIFS(Data!$A$2:$A$3627,Dashboard!$B$7,Data!$B$2:$B$3627,Dashboard!$C$7,Data!$E$2:$E$3627,$A9,Data!$F$2:$F$3627,$B9,Data!$G$2:$G$3627,"Need Improvement") | D9: =COUNTIFS(Data!$A$2:$A$3627,Dashboard!$B$7,Data!$B$2:$B$3627,Dashboard!$C$7,Data!$E$2:$E$3627,$A9,Data!$F$2:$F$3627,$B9,Data!$G$2:$G$3627,"All is Well") | E9: =C9+D9 | F9: =IFERROR(C9/E9,0) | G9: =C9+(ROW()/100000)
A10: Infra Check | B10: Check all CCTV cameras; if any are not working, ask the AH to troubleshoot or call the vendor. | C10: =COUNTIFS(Data!$A$2:$A$3627,Dashboard!$B$7,Data!$B$2:$B$3627,Dashboard!$C$7,Data!$E$2:$E$3627,$A10,Data!$F$2:$F$3627,$B10,Data!$G$2:$G$3627,"Need Improvement") | D10: =COUNTIFS(Data!$A$2:$A$3627,Dashboard!$B$7,Data!$B$2:$B$3627,Dashboard!$C$7,Data!$E$2:$E$3627,$A10,Data!$F$2:$F$3627,$B10,Data!$G$2:$G$3627,"All is Well") | E10: =C10+D10 | F10: =IFERROR(C10/E10,0) | G10: =C10+(ROW()/100000)
A11: Infra Check | B11: Check for any scrap material and get it cleared, with support of Admin | C11: =COUNTIFS(Data!$A$2:$A$3627,Dashboard!$B$7,Data!$B$2:$B$3627,Dashboard!$C$7,Data!$E$2:$E$3627,$A11,Data!$F$2:$F$3627,$B11,Data!$G$2:$G$3627,"Need Improvement") | D11: =COUNTIFS(Data!$A$2:$A$3627,Dashboard!$B$7,Data!$B$2:$B$3627,Dashboard!$C$7,Data!$E$2:$E$3627,$A11,Data!$F$2:$F$3627,$B11,Data!$G$2:$G$3627,"All is Well") | E11: =C11+D11 | F11: =IFERROR(C11/E11,0) | G11: =C11+(ROW()/100000)
A12: Infra Check | B12: Check for any pending infra repairs. | C12: =COUNTIFS(Data!$A$2:$A$3627,Dashboard!$B$7,Data!$B$2:$B$3627,Dashboard!$C$7,Data!$E$2:$E$3627,$A12,Data!$F$2:$F$3627,$B12,Data!$G$2:$G$3627,"Need Improvement") | D12: =COUNTIFS(Data!$A$2:$A$3627,Dashboard!$B$7,Data!$B$2:$B$3627,Dashboard!$C$7,Data!$E$2:$E$3627,$A12,Data!$F$2:$F$3627,$B12,Data!$G$2:$G$3627,"All is Well") | E12: =C12+D12 | F12: =IFERROR(C12/E12,0) | G12: =C12+(ROW()/100000)
A13: Infra Check | B13: Check whether any fire extinguishers have expired (check the needle and expiry date both). | C13: =COUNTIFS(Data!$A$2:$A$3627,Dashboard!$B$7,Data!$B$2:$B$3627,Dashboard!$C$7,Data!$E$2:$E$3627,$A13,Data!$F$2:$F$3627,$B13,Data!$G$2:$G$3627,"Need Improvement") | D13: =COUNTIFS(Data!$A$2:$A$3627,Dashboard!$B$7,Data!$B$2:$B$3627,Dashboard!$C$7,Data!$E$2:$E$3627,$A13,Data!$F$2:$F$3627,$B13,Data!$G$2:$G$3627,"All is Well") | E13: =C13+D13 | F13: =IFERROR(C13/E13,0) | G13: =C13+(ROW()/100000)
... A50: Aspirant Interaction | B50: Ask a few relevant screening questions to support the 10th-day report and remove non-serious candidates, explaining to them the reasons. | C50: =COUNTIFS(Data!$A$2:$A$3627,Dashboard!$B$7,Data!$B$2:$B$3627,Dashboard!$C$7,Data!$E$2:$E$3627,$A50,Data!$F$2:$F$3627,$B50,Data!$G$2:$G$3627,"Need Improvement") | D50: =COUNTIFS(Data!$A$2:$A$3627,Dashboard!$B$7,Data!$B$2:$B$3627,Dashboard!$C$7,Data!$E$2:$E$3627,$A50,Data!$F$2:$F$3627,$B50,Data!$G$2:$G$3627,"All is Well") | E50: =C50+D50 | F50: =IFERROR(C50/E50,0) | G50: =C50+(ROW()/100000)

Sheet Lists
A1: All Managers | B1: All Centres | C1: All Centres | D1: All Centres | E1: All Centres | F1: All Centres | G1: All Centres | H1: All Centres | I1: All Centres | J1: All Centres | K1: All Centres
A2: Amit Chakraborty | B2: Akkayapalem | C2: Alambagh | D2: Daryaganj | E2: Bachupally | F2: Belapur | G2: Ambattur | H2: Akkayapalem | I2: CFRSI-Chandanagar | J2: Bommanahalli | K2: Baramunda(Bhubaneswar)
A3: Barna | B3: Alambagh | C3: Baccha Park | D3: Gurgaon | E3: Gachibowli | F3: Bund Garden Pune | G3: Coimbatore | H3: Anakapalli | I3: Karimnagar | J3: Bommanahalli | K3: Berhampur
A4: Bhargav Challa | B4: Ambattur | C4: Barasat | D4: Lakhe Nagar Raipur | E4: Nalgonda | F4: Chinchwad - Pune | G4: Velachery-Accenture Additional Grant | H4: CFRSI Chennai | I4: Tech jobs-Miyapur | J4: CFRSI - Bengaluru
A5: Gagandeep Singh Sachar | B5: Anakapalli | C5: Bareilly | D5: NOIDA Sec 63 | E5: Secunderabad | F5: Jogeshwari | H5: Gajuwaka | J5: Electronic City
A6: Mahaboob Basha | B6: Baccha Park | C6: Danapur | D6: Nanda Nagar center | E6: Uppal | F6: Pune Green | H6: Grow Green Ambattur | J6: Hebbal
A7: Phani | B7: Bachupally | C7: Dankuni | D7: Narmada Nagar Bilaspur | E7: Warangal | F7: Swargate | H7: Guindy Solar | J7: Hoskote
A8: Raghavender Rao | B8: Baramunda(Bhubaneswar) | C8: Dumdum | D8: Nehru Nagar Durg | F8: Thane | H8: Guntur | J8: Hoskote
A9: S Jakir | B9: Barasat | C9: Ghaziabad | D9: Peeragarhi | F9: Vadodara Citi | H9: Kochi CITI | J9: Hubli
A10: Sanjay Kumar Tarai | B10: Bareilly | C10: Kidwainagar | D10: Sarita Vihar | F10: Vadodara HQHCS | H10: Kochi Women | J10: Jalahalli
B11: Belapur | C11: Lucknow-Indiranagar | D11: Shahdara | F11: Vasai | H11: Krishnalanka | J11: K R Puram
B12: Berhampur | D12: Shanti Nagar Raipur CITI | H12: MG Road (Vijayawada) | J12: Marathahalli
B13: Bommanahalli | H13: Srikakulam | J13: Nelamangala
B14: Bommanahalli | H14: Trivendrum CITI | J14: Thanisandra
B15: Bund Garden Pune | H15: Vijayanagaram | J15: Uttarahalli
B16: CFRSI - Bengaluru | J16: Yelahanka
B17: CFRSI Chennai
B18: CFRSI-Chandanagar
B19: Chinchwad - Pune
B20: Coimbatore
B21: Danapur
B22: Dankuni
B23: Daryaganj
B24: Dumdum
B25: Electronic City
B26: Gachibowli
B27: Gajuwaka
B28: Ghaziabad
... B75: Yelahanka
